Workbook

Sheet #Sommaire
A2: ID unique | B2: Objet(s) niveau 1 (MDD) | C2: Libellé de la donnée (MDD) | D2: Description | E2: Référentiel source | F2: Nom de la nomenclature | G2: Lien | H2: Statut Nomenclature | I2: RC-EDA | J2: RS-EDA | K2: RS-EDA-MAJ | L2: RS-RPIS | M2: RS-BPV | N2: RS-RI | O2: RS-DR | P2: RS-RR | Q2: RS-SR | R2: RC-REF
A3: HubSante.filiere | B3: Filiere | C3: Filiere | D3: =Filiere!$B$5 -> Décrit la filière compétente pour traiter le dossier. | E3: =Filiere!$B$2 -> ENUM | F3: =Filiere!$B$3 -> FILIERE | G3: Lien nomenclature | H3: V1 validée métier | J3: X | K3: X
A4: HubSante.intervention | B4: Type d'intervention | C4: Type d'intervention | D4: ='Type d''intervention'!$B$5 -> Décrit le type d'intervention (primaire, secondaire, etc.) | E4: ='Type d''intervention'!$B$2 -> ENUM | F4: ='Type d''intervention'!$B$3 -> TYPE_Intervention | G4: Lien nomenclature | H4: V1 validée métier | J4: X
A5: HubSante.origine | B5: Qualification de l'affaire/dossier | C5: Origine de l'appel | D5: ='Origine de l''appel'!$B$5 -> Décrit l'origine de l'appel | E5: ='Origine de l''appel'!$B$2 -> ENUM | F5: ='Origine de l''appel'!$B$3 -> ORIGINE | G5: Lien nomenclature | H5: V1 validée métier | J5: X
A6: HubSante.fait | B6: Qualification de l'affaire/dossier | C6: Nature de fait | D6: ='Nature de fait'!$B$5 -> Décrit la nature de fait de l'affaire/dossier | E6: ='Nature de fait'!$B$2 -> CISU | F6: ='Nature de fait'!$B$3 -> Code_Nature_de_fait | G6: Lien nomenclature | H6: V2.3 validée CISU | I6: X | J6: X | L6: X
A7: HubSante.lieu | B7: Qualification de l'affaire/dossier | C7: Type de lieu | D7: ='Type de lieu'!$B$5 -> Décrit le type de lieu où se situe l'affaire/dossier | E7: ='Type de lieu'!$B$2 -> CISU | F7: ='Type de lieu'!$B$3 -> Code_Type_de_lieu | G7: Lien nomenclature | H7: V2.3 validée CISU | I7: X | J7: X | L7: X | M7: X
A8: HubSante.risque | B8: Qualification de l'affaire/dossier | C8: Risque, menace et sensibilité | D8: ='Risque, menace et sensibilité'!$B$5 -> Décrit les risques, menaces ou sensibilités de l'affaire/dossier | E8: ='Risque, menace et sensibilité'!$B$2 -> CISU | F8: ='Risque, menace et sensibilité'!$B$3 -> Code_Risque-Menace-Sensibilité | G8: Lien nomenclature | H8: V2.3 validée CISU | I8: X | J8: X | K8: X
A9: HubSante.motif | B9: Qualification de l'affaire/dossier | C9: Motif de recours médico-secouriste | D9: ='Motif de recours médico-secouri'!$B$5 -> Décrit le motif de recours médico-secouriste. | E9: ='Motif de recours médico-secouri'!$B$2 -> CISU | F9: ='Motif de recours médico-secouri'!$B$3 -> Code_Motif_patient-victime | G9: Lien nomenclature | H9: V2.3 validée CISU | I9: X | J9: X | L9: X
A10: HubSante.etat | B10: Qualification de l'affaire/dossier | C10: Etat du dossier | D10: ='Etats du dossier'!$B$5 -> Décrit la filière compétente pour traiter le dossier. | E10: ='Etats du dossier'!$B$2 -> ENUM | F10: ='Etats du dossier'!$B$3 -> Etats_Dossier | G10: Lien nomenclature | H10: V1 validée métier | J10: X | K10: X
A11: HubSante.nbVictimes | B11: Qualification de l'affaire/dossier | C11: Nombre de patients-victimes | D11: ='Nombre de patients-victimes'!$B$5 -> Décrit le nombre de patient/victimes | E11: ='Nombre de patients-victimes'!$B$2 -> ENUM | F11: ='Nombre de patients-victimes'!$B$3 -> NOMBRE_Patient_Victime | G11: Lien nomenclature | H11: V1 validée métier | I11: X
A12: HubSante.patient | B12: Qualification de l'affaire/dossier | C12: Type du patient-victime | D12: ='Type du patient-victime'!$B$5 -> Décrit le type de patient/victime principal | E12: ='Type du patient-victime'!$B$2 -> ENUM | F12: ='Type du patient-victime'!$B$3 -> TYPE_Patient_Victime | G12: Lien nomenclature | H12: V1 validée métier | I12: X
A13: HubSante.attribution | B13: Qualification de l'affaire/dossier | C13: Attribution du dossier | D13: ='Attribution du dossier'!$B$5 -> Décrit le type de dossier, et son attribution | E13: ='Attribution du dossier'!$B$2 -> SI-SAMU | F13: ='Attribution du dossier'!$B$3 -> DEVENIRD | G13: Lien nomenclature | H13: V1 validée métier | J13: X
A14: HubSante.priorite | B14: Qualification de l'affaire/dossier | C14: Priorité de régulation médicale | D14: ='Priorité de régulation médicale'!$B$5 -> Décrit la priorité de régulation médicale. | E14: ='Priorité de régulation médicale'!$B$2 -> SI-SAMU | F14: ='Priorité de régulation médicale'!$B$3 -> PRIORITE | G14: Lien nomenclature | H14: V1 validée métier | J14: X | K14: X
A15: HubSante.idLieu | B15: Localisation | C15: Lieu - Source ou type d'id | D15: ='Lieu - Source ou type d''id'!$B$5 -> Décrit le type d'idenfiant possible pour un lieu (société / établissement) | E15: ='Lieu - Source ou type d''id'!$B$2 -> ENUM | F15: ='Lieu - Source ou type d''id'!$B$3 -> SOURCE_Id_Lieu | G15: Lien nomenclature | H15: V1 validée métier | I15: X | J15: X | K15: X
A16: HubSante.precision | B16: Localisation | C16: Precision | D16: =Precision!$B$5 -> Décrit le niveau de précision des coordonnées GPS envoyées | E16: =Precision!$B$2 -> ENUM | F16: =Precision!$B$3 -> PRECISION | G16: Lien nomenclature | H16: V1 validée métier | I16: X | J16: X
A17: HubSante.systeme | B17: Localisation | C17: Nom de la source | D17: ='Nom de la source'!$B$5 -> Décrit le système fournissant le localisant | E17: ='Nom de la source'!$B$2 -> ENUM | F17: ='Nom de la source'!$B$3 -> SOURCE_Loc | G17: Lien nomenclature | H17: V1 validée métier | I17: X | J17: X | K17: X
A18: HubSante.objetSource | B18: Localisation | C18: Type d'objet | D18: ='Type d''objet'!$B$5 -> Décrit le type d'objet dans le système | E18: ='Type d''objet'!$B$2 -> ENUM | F18: ='Type d''objet'!$B$3 -> TYPE_Objet_Sys | G18: Lien nomenclature | H18: V1 validée métier | I18: X | J18: X | K18: X
A19: HubSante.signalement | B19: Alerte initiale | C19: Signalement | D19: =Signalement!$B$5 -> Décrit le niveau de signalement de l'alerte | E19: =Signalement!$B$2 -> ENUM | F19: =Signalement!$B$3 -> SIGNALEMENT | G19: Lien nomenclature | H19: V1 validée métier | I19: X
A20: HubSante.canal | B20: Alerte initiale | C20: Canal | D20: =Canal!$B$5 -> Décrit le type de canal utilisé pour le contact | E20: =Canal!$B$2 -> ENUM | F20: =Canal!$B$3 -> CONTACT_Canal | G20: Lien nomenclature | H20: V1 validée métier | I20: X | J20: X
A21: HubSante.typeCom | B21: Alerte initiale | C21: Type de contact | D21: ='Type de contact'!$B$5 -> Décrit le type de contact | E21: ='Type de contact'!$B$2 -> ENUM | F21: ='Type de contact'!$B$3 -> CONTACT_Type | G21: Lien nomenclature | H21: V1 validée métier | I21: X | J21: X | K21: X
A22: HubSante.langue | C22: Langue | D22: =Langue!B5 -> Décrit la langue parlée par l'appelant / le requérant. Source : https://www.loc.gov/standards/iso639-2/php/code_list.php | E22: =Langue!B2 -> ISO-639.1 | F22: =Langue!B3 -> LANGUE | G22: Lien nomenclature | H22: Validée | I22: X | J22: X
A23: HubSante.typeAppelant | B23: Alerte initiale | C23: Type de requérant | D23: ='Type de requérant'!$B$5 -> Décrit le type de requérant/appelant | E23: ='Type de requérant'!$B$2 -> SI-SAMU | F23: ='Type de requérant'!$B$3 -> TYPAPPLT | G23: Lien nomenclature | H23: V1 validée métier | I23: X | J23: X
A24: HubSante.communication | B24: Alerte initiale | C24: Difficultés de communication | D24: ='Difficultés de communication'!$B$5 -> Décrit les difficultés de communication potentielles du requérant/appelant | E24: ='Difficultés de communication'!$B$2 -> SI-SAMU | F24: ='Difficultés de communication'!$B$3 -> PBAPL | G24: Lien nomenclature | H24: V1 validée métier | I24: X | J24: X
A25: HubSante.typeIdPatient | B25: Patient | C25: Patient - type d'Id | D25: ='Patient - type d''Id'!$B$5 -> Décrit le type d'identifiant fourni | E25: ='Patient - type d''Id'!$B$2 -> ENUM | F25: ='Patient - type d''Id'!$B$3 -> TYPE_Id_Patient | G25: Lien nomenclature | H25: V1 validée métier | J25: X | K25: X | M25: X
A26: HubSante.sexe | B26: Patient | C26: Sexe | D26: =Sexe!$B$5 -> Décrit le sexe du patient | E26: =Sexe!$B$2 -> NOS | F26: =Sexe!$B$3 -> NOMENC_SEXE | G26: Lien nomenclature | H26: Validée | I26: X | J26: X | K26: X | L26: X | M26: X
A27: HubSante.niveauSoin | B27: Qualification / Patient | C27: Niveau de soin | D27: ='Niveau de soin'!$B$5 -> Décrit le niveau de soins : le plus grave est retenu pour qualifier le dossier/affaire. Pour chaque patient/victime, le motif spécifique est indiqué. | E27: ='Niveau de soin'!$B$2 -> SI-SAMU | F27: ='Niveau de soin'!$B$3 -> GRAVITE | G27: Lien nomenclature | H27: V1 validée métier | J27: X | K27: X
A28: HubSante.role | B28: Observation médicale | C28: Role | D28: =Role!$B$5 -> Décrit le rôle de l'opérateur dans l'organisation à laquelle il appartient | E28: =Role!$B$2 -> ENUM | F28: =Role!$B$3 -> ROLE | G28: Lien nomenclature | H28: V1 validée métier | J28: X | K28: X | M28: X
A29: HubSante.typeDecision | B29: Décisions | C29: Type de decision | D29: ='Type de decision'!$B$5 -> Décrit le type de décision prise | E29: ='Type de decision'!$B$2 -> SI-SAMU | F29: ='Type de decision'!$B$3 -> TYPEDEC | G29: Lien nomenclature | H29: V1 validée métier | J29: X | K29: X
A30: HubSante.typeRessource | B30: Décisions / Ressource engagée | C30: Type de ressource | D30: ='Type de ressource'!$B$5 -> Décrit le type de moyen/ressources, dans un sens plus large que type de vecteur/véhicule. N.B. dans OPG pour les message EMSI. | E30: ='Type de ressource'!$B$2 -> SI-SAMU | F30: ='Type de ressource'!$B$3 -> TYPE_MOYEN | G30: Lien nomenclature | H30: V1 validée métier | J30: X | K30: X | L30: X | P30: X
A31: HubSante.typeVecteur | B31: Décisions / Ressource engagée | C31: Type de vecteurs | D31: ='Type de vecteurs'!$B$5 -> Décrit le type de vecteur/véhicule ou de ressource mobilisée, avec plus de précision que simplement le type de ressources. Utilisée exclusivement en inter-santé (cf. EMSI-OPG pour 15-NexSIS) | E31: ='Type de vecteurs'!$B$2 -> SI-SAMU | F31: ='Type de vecteurs'!$B$3 -> TYPE_VECTEUR | G31: Lien nomenclature | H31: V1 validée métier | L31: X | N31: X | P31: X
A32: HubSante.typePEC | B32: Ressource engagée | C32: Niveau de prise en charge | D32: ='Niveau de prise en charge'!$B$5 -> Décrit le niveau de prise en charge exigé. | E32: ='Niveau de prise en charge'!$B$2 -> SI-SAMU | F32: ='Niveau de prise en charge'!$B$3 -> NIVSOIN | G32: Lien nomenclature | H32: V1 validée métier | L32: X | N32: X
A33: HubSante.typeOrientation | B33: Décisions | C33: Type d'orientation | D33: ='Type de destination'!$B$5 -> Décrit la filière compétente pour traiter le dossier. | E33: ='Type de destination'!$B$2 -> ENUM | F33: ='Type de destination'!$B$3 -> TYPE_Destination | G33: Lien nomenclature | H33: V1 validée métier | J33: X | K33: X
A34: HubSante.effet | B34: Demande de ressource | C34: Effet à obtenir | D34: ='Effet à obtenir'!$B$5 -> Décrit les effets à obtenir utilisés uniquement entre SAMU, en intersanté. | E34: ='Effet à obtenir'!$B$2 -> CISU | F34: ='Effet à obtenir'!$B$3 -> Code_Effet_a_obtenir | G34: Lien nomenclature | H34: V2.3 validée CISU | O34: X
A35: HubSante.cadre | B35: Demande de ressource | C35: Cadre conventionnel | D35: ='Cadre conventionnel'!$B$5 -> Décrit le cadre conventionnel dans lequel s'inscrit une demande de ressources. Codes inter-santé uniquement (voir EMSI pour lien 15-Nexsis). | E35: ='Cadre conventionnel'!$B$2 -> CISU | F35: ='Cadre conventionnel'!$B$3 -> CADRE_CONV | G35: Lien nomenclature | H35: V2.3 validée CISU | O35: X
A36: HubSante.delai | B36: Demande de ressource | C36: Delai d'intervention | D36: ='Delai d''intervention'!$B$5 -> Décrit le délai d'intervention attendu ou souhaité pour une ressource ou un vecteur. | E36: ='Delai d''intervention'!$B$2 -> SI-SAMU | F36: ='Delai d''intervention'!$B$3 -> DELAI | G36: Lien nomenclature | H36: V1 validée métier | O36: X | P36: X
A37: HubSante.etatDemande | B37: resourcesRequest | C37: Etat annulation | D37: ='Annulation DR'!$B$5 -> Décrit l'état de l'annulation de demande de ressources | E37: ='Annulation DR'!B2 -> ENUM | F37: ='Annulation DR'!B3 -> STATUS_DR | G37: Lien nomenclature | H37: V1 validée métier | O37: X
A38: HubSante.reponseDemande | B38: Réponse à la demande de ressources | C38: Reponse demande ressources | D38: ='Reponse demande ressources'!$B$5 -> Décrit la réponse à une demande de ressources | E38: ='Reponse demande ressources'!$B$2 -> ENUM | F38: ='Reponse demande ressources'!$B$3 -> REPONSE | G38: Lien nomenclature | H38: V1 validée métier | P38: X
A39: HubSante.statutVecteur | B39: Ressource engagée / resourcesStatus | C39: Statut du vecteur | D39: ='Statut du vecteur'!$B$5 -> Décrit le statut du vecteur/véhicule mobilisé | E39: ='Statut du vecteur'!$B$2 -> SI-SAMU | F39: ='Statut du vecteur'!$B$3 -> STATUS_VECTEUR | G39: Lien nomenclature | H39: V1 validée métier | N39: X | Q39: X
A40: HubSante.etape | C40: Etape d'intégration du dossier | D40: ='Etape message'!B5 -> Décrit les différentes étapes d'intégration et de consultation du dossier dans un système | E40: ='Etape message'!B2 -> ENUM | F40: ='Etape message'!B3 -> Etape_Message | G40: Lien nomenclature | H40: V1 hub Santé | R40: X

Sheet Filiere
A1: Identifiant nomenclature | B1: HubSante.filiere
A2: Référentiel nomenclature | B2: ENUM
A3: Nom Nomenclature | B3: FILIERE
A4: Nombre de niveau | B4: 1
A5: Description | B5: Décrit la filière compétente pour traiter le dossier.
A6: Code | B6: Libellé niveau 1 | C6: Libellé niveau 2 | D6: Description | E6: Commentaire
A7: AMU | B7: Aide Médicale d'Urgence | D7: Filière dédiée à l'aide médicale d'urgence
A8: NEONAT | B8: Néonatalité | D8: Filière dédiée à la néonatalité
A9: PSY | B9: Psychiatrie | D9: Filière dédiée à la psychiatrie
A10: SNP | B10: Soins Non Programmés | D10: Filière dédiée aux soins non programmés

Sheet Type d'intervention
A1: Identifiant nomenclature | B1: HubSante.intervention
A2: Référentiel nomenclature | B2: ENUM
A3: Nom Nomenclature | B3: TYPE_Intervention
A4: Nombre de niveau | B4: 1
A5: Description | B5: Décrit le type d'intervention (primaire, secondaire, etc.)
A6: Code | B6: Libellé niveau 1 | C6: Libellé niveau 2 | D6: Description | E6: Commentaire
A7: T1 | B7: Primaire | D7: Prise en charge médicale spécialisée d’un ou de plusieurs patients ne se trouvant pas admis dans un établissement de santé et dont l’état requiert de façon urgente une expertise médicale pour des soins d’urgences ou de réanimation et pour leur orientation.
A8: T2-INTER | B8: Transfert Inter Hospitalier | D8: Prise en charge médicale spécialisée d’un patient hospitalisé ou pris en charge par un service (d’urgences ou non), au sein d’un établissement de santé vers un établissement de santé ne faisant pas partie de la même entité juridique, que le transport ait finalement lieu ou non.
A9: T2-INTRA | B9: Transfert Intra Hospitalier | D9: Prise en charge médicale spécialisée d’un patient hospitalisé ou pris en charge par un service (d’urgences ou non), au sein d’un établissement de santé vers n même établissement de santé ou entre deux établissements de santé appartenant à la même entité juridique.
A10: T3 | B10: Retour | D10: Prise en charge médicale spécialisée d’un patient hospitalisé en vue de son retour à son domicile ou dans une structure n’étant pas un établissement de santé (par exemple un EHPAD).
A11: T4 | B11: Rapat/Evasan | D11: Prise en charge médicale spécialisée d’un patient en vue de son transport le plus souvent vers un établissement de soins, par exemple dans le cadre d’un rapprochement familial.

Sheet Origine de l'appel
A1: Identifiant nomenclature | B1: HubSante.origine
A2: Référentiel nomenclature | B2: ENUM
A3: Nom Nomenclature | B3: ORIGINE
A4: Nombre de niveau | B4: 1
A5: Description | B5: Décrit l'origine de l'appel
A6: Code | B6: Libellé niveau 1 | C6: Libellé niveau 2 | D6: Description | E6: Commentaire
A7: 15 | B7: Ligne 15 | D7: Le requérant a contacté directement le CRRA en composant le 15.
A8: 116117 | B8: Ligne PDSA | D8: Le requérant a contacté directement le CRRA en composant le numéro d’une ligne PDSA (116117 et autres lignes encore fonctionnelles)
A9: AUTOCOM | B9: Ligne hôpital | D9: Le requérant a contacté directement le CRRA en composant un numéro interne de l’établissement de santé siège du Samu Centre 15.
A10: 112 | B10: Ligne 112 | D10: Le requérant a contacté directement le CRRA en composant le numéro 112
A11: 115 | B11: Ligne 115 | D11: Le requérant a contacté directement le CRRA en composant le numéro 115
A12: CRRA | B12: CRRA (autres lignes) | D12: Le requérant a contacté directement le CRRA en composant un autre numéro pour contacter le Samu – Centre 15.
A13: AUTREC15 | B13: Autre CRRA | D13: Le requérant a contacté en premier un autre Samu Centre 15 qui a retransmis l’appel au CRRA
A14: CTA-CONF | B14: CTA-CODIS en conf | D14: Le requérant a contacté en premier le ou les CTA CODIS correspondant(s) habituel(s) du Samu qui a retransmis l’appel au CRRA ; appel avec mise en interconnexion par conférence.
A15: CTA-PI | B15: CTA-CODIS pour info | D15: Le requérant a contacté en premier le ou les CTA CODIS correspondant(s) habituel(s) du Samu qui a retransmis l’appel au CRRA ; appel avec simple information.
A16: AUTRECTA | B16: Autre CTA-CODIS | D16: Le requérant a contacté en premier un CTA CODIS distant qui n’est pas un correspondant habituel du Samu qui a retransmis l’appel au CRRA.
A17: CNR | B17: CNR 114 | D17: Le requérant a contacté en premier le centre national relais pour les sourds et malentendants qui a retransmis l’appel au CRRA.
A18: FDO | B18: CORG, CIC | D18: Le requérant a contacté en premier un standard de forces de l’ordre (police, gendarmerie, …) qui a retransmis l’appel au CRRA.
A19: SNATED | B19: Ligne 119 (SNATED) | D19: Le requérant a contacté en premier le standard de la protection de l’enfance qui a retransmis l’appel au CRRA.
A20: PDSSOS | B20: Asso PDSA et SOS | D20: Le requérant a contacté en premier un standard d’une association de PDSA, type SOS médecins ou autres qui a retransmis l’appel au CRRA.
A21: TELASSIST | B21: Téléassistance | D21: Le requérant a contacté en premier une structure de télésurveillance ou d’assistance médicale qui a retransmis l’appel au CRRA.
A22: CROSS | B22: CROSS | D22: Le requérant a contacté en premier une structure publique d’urgence type CROSS maritime qui a retransmis l’appel au CRRA.
A23: PUBLIC | B23: Autre centre d'appel | D23: Le requérant a contacté en premier une structure publique d’urgence type associations ne participant pas à la PDSA, … qui a retransmis l’appel au CRRA.
... A25: AUTRE | B25: Autre structure | D25: Si le central d’appel d’urgence est déterminé mais ne fait pas partie des choix précédents ou lorsque l’information n’est pas disponible.

Sheet Nature de fait
A1: Identifiant nomenclature | B1: HubSante.fait
A2: Référentiel nomenclature | B2: CISU
A3: Nom Nomenclature | B3: Code_Nature_de_fait
A4: Nombre de niveau | B4: 3
A5: Description | B5: Décrit la nature de fait de l'affaire/dossier
A6: Code | B6: Libellé niveau 1 | C6: Libellé niveau 2 | D6: Libellé niveau 3 | E6: Description | F6: Commentaire
A7: C01.00.00 | B7: Accident de la circulation
A8: C01.01.00 | C8: Accident routier non suivi de feu
A9: C01.01.01 | D9: Accident routier véhicule léger / fourgon, non suivi de feu | E9: Catégorie de véhicules qui regroupe les voitures de tourisme et les véhicules utilitaires (jusqu'à 3,5 tonnes)
A10: C01.01.02 | D10: Accident routier camion de marchandises, non suivi de feu | E10: Poids lourd de plus de 3,5 tonnes affecté au transport de biens et embarquant donc un nombre réduit de passagers
A11: C01.01.03 | D11: Accident routier bus / car / autocar, non suivi de feu | E11: Véhicule de grande dimension affecté au transport de passagers
A12: C01.01.04 | D12: Accident routier 2-roues, non suivi de feu | E12: Tout véhicule à deux roues, avec ou sans moteur (bicyclette, cyclomoteur, motocyclette, …), l’implication d'un 2 roues « l'emporte » sur les autres types de moyens routiers
A13: C01.01.05 | D13: Accident routier piéton, non suivi de feu | E13: L’implication d'un piéton « l'emporte » sur les autres types de moyens routiers
A14: C01.01.06 | D14: Accident routier : carambolage non suivi de feu | E14: Série de chocs, de collisions impliquant 4 véhicules et plus, la notion de carambolage « l'emporte » sur les autres types d'accidents routiers
A15: C01.01.07 | D15: Accident routier d'engin de chantier/agricole, non suivi de feu
A16: C01.06.00 | C16: Accident routier suivi de feu
A17: C01.06.01 | D17: Accident routier véhicule léger / fourgon, suivi de feu
A18: C01.06.02 | D18: Accident routier poids lourd, suivi de feu
A19: C01.06.03 | D19: Accident routier bus / car / autocar, suivi de feu
A20: C01.06.04 | D20: Accident routier avec plusieurs véhicules légers, suivi de feu
A21: C01.06.05 | D21: Accident routier : carambolage suivi de feu
A22: C01.02.00 | C22: Accident ferroviaire | E22: L’implication d'un train « l'emporte » sur les moyens routiers
A23: C01.02.01 | D23: Accident train de voyageurs | E23: Tout moyen de transport de personnes par voie ferroviaire
A24: C01.02.02 | D24: Accident train de marchandises | E24: Tout moyen de transport de marchandises par voie ferroviaire
A25: C01.02.03 | D25: Collision train - piéton
A26: C01.02.04 | D26: Collision tramway - piéton
A27: C01.02.05 | D27: Déraillement train de voyageurs
A28: C01.02.06 | D28: Déraillement train de marchandises
A29: C01.02.07 | D29: Déraillement tram, tramway
A30: C01.03.00 | C30: Accident maritime ou fluvial
A31: C01.03.05 | D31: Accident bateau de plaisance / sports nautiques
A32: C01.03.01 | D32: Accident ferry / paquebot | E32: Tout moyen de transport de personnes par voie maritime, avec ou sans moteur (voilier, navire de plaisance, paquebot de croisière, …)
A33: C01.03.02 | D33: Accident bateau de marchandises | E33: Tout moyen de transport de marchandises par voie maritime, avec ou sans moteur (barque, navire de pêche, cargo, …)
A34: C01.03.03 | D34: Accident bateau de pêche
A35: C01.03.04 | D35: Accident bateau de guerre
A36: C01.04.00 | C36: Accident aérien
A37: C01.04.01 | D37: Accident aéronef de marchandises | E37: Tout moyen de transport de marchandises par voie aérienne embarquant au moins 1 pilote à son bord
A38: C01.04.02 | D38: Accident aéronef de ligne | E38: Tout moyen de transport de personnes par voie aérienne embarquant au moins 1 pilote à son bord
A39: C01.04.03 | D39: Accident aéronef militaire | E39: Tout moyen de transport militaire par voie aérienne embarquant au moins 1 pilote à son bord
A40: C01.04.04 | D40: Accident de drone | E40: Petit avion sans équipage embarqué, télécommandé ou programmé
A41: C01.04.05 | D41: Accident aéronef de tourisme
A42: C01.04.06 | D42: Accident ULM / planeur / mongolfiière
A43: C01.05.00 | C43: Autre type d’accident de circulation
A44: C02.00.00 | B44: Atteinte aux personnes
A45: C02.01.00 | C45: Attentat /tuerie de masse | E45: Un ou plusieurs actes de violence de nature à mettre en péril les institutions de la République ou à porter atteinte à l'intégrité du territoire national (Article 412-1 du Code Pénal) - Dont attentat sur autorité / tuerie planifiée
A46: C02.02.00 | C46: Prise d’otage | E46: Détention de personnes contre leur volonté, le plus souvent dans un but revendicatif
A47: C02.17.00 | C47: Découverte de cadavre/mort suspecte
A48: C02.17.01 | D48: Découverte de cadavre
A49: C02.17.02 | D49: Mort suspecte
A50: C02.03.00 | C50: Homicide ou infanticide
A51: C02.03.01 | D51: Homicide | E51: Meurtre volontaire ou involontaire d’un autre être humain
A52: C02.03.02 | D52: Infanticide | E52: Meurtre volontaire ou involontaire d’un autre être humain âgé de moins de 15 ans
A53: C02.04.00 | C53: Enlèvement / séquestration
A54: C02.04.01 | D54: Alerte enlèvement | E54: Enlèvement d’un enfant sujet au déclenchement du dispositif Alerte Enlèvement par le procureur de la République territorialement compétent > 4 critères de déclenchement : * Enlèvement avéré (il ne s’agit pas d’une disparition, même inquiétante) * La victime est mineure * La vie ou l’intégrité physique de l’enfant est en danger
A55: C02.04.02 | D55: Enlèvement | E55: Enlèvement d’une personne (il ne s’agit pas d’une disparition, même inquiétante)
A56: C02.04.03 | D56: Séquestration | E56: Action de retenir une personne enfermée contre son gré en dehors de toute autorité légale en usant de violence, de ruse ou de la menace
A57: C02.05.00 | C57: Pathologie / maladie
A58: C02.05.01 | D58: Pathologie médicale | E58: Tout problème médical autre qu’obstétrique ou psychiatrique (liste détaillée disponible dans les motifs de recours médico-secouriste)
A59: C02.05.02 | D59: Pathologie obstétrique | E59: Tout problème médical relatif à la grossesse et à l'accouchement
A60: C02.18.00 | C60: Problème psychiatrique, menace de suicide | E60: Tout problème psychiatrique (dont Hospitalisation sans consentement) ou psychologique, y compris les personnes dépressives mais SANS passage à l'acte suicidaire
A61: C02.06.00 | C61: Intoxication
A62: C02.06.01 | D62: Intoxication alimentaire collective (TIAC) | E62: Apparition d’au moins deux cas similaires d’une symptomatologie, en général gastro-intestinale, dont on peut rapporter la cause à une même origine alimentaire
A63: C02.06.02 | D63: Intoxication CO
A64: C02.07.00 | C64: Personne exposée (à)
A65: C02.07.01 | D65: Personne exposée à la chaleur / canicule
A66: C02.07.02 | D66: Personne exposée au froid
A67: C02.07.03 | D67: Personne exposée aux flammes / à la fumée
A68: C02.07.04 | D68: Personne exposée aux produits chimiques ou toxiques / Accident technologique / Intervention à caractère NRBC | E68: NRBC : nucléaire, radiologique, biologique et/ou chimique
A69: C02.07.05 | D69: Personne électrisée
A70: C02.07.06 | D70: Personne foudroyée
A71: C02.07.07 | D71: Personne exposée à des rayonnements ou radioéléments
A72: C02.08.00 | C72: Traumatisme / Accident
A73: C02.08.01 | D73: Accident avec machine professionnelle / Accident du travail | E73: A l’occasion et par le fait du travail dans un milieu professionnel
A74: C02.08.02 | D74: Accident domestique | E74: Tout accident (traumatisme, intoxication, brûlure, …) survenu à l’intérieur d’un domicile ou de ses dépendances, impliquant une ou plusieurs victimes qui se livraient à une occupation non rémunérée > Dont électroménager, appareil domestique, jouet
A75: C02.08.03 | D75: Autre accident (hors sport et loisirs)
A76: C02.08.04 | D76: Traumatisme par arme à feu
A77: C02.08.05 | D77: Traumatisme par objet tranchant ou perforant
A78: C02.08.06 | D78: Blessures, piqûre, morsure d'animaux
A79: C02.08.07 | D79: Pendaison / strangulation accidentelle
A80: C02.08.08 | D80: Etouffement / fausse route
A81: C02.09.00 | C81: Accident de sport ou de loisirs
A82: C02.09.01 | D82: Accident de chasse
A83: C02.09.02 | D83: Accident de plongée
A84: C02.09.03 | D84: Accident de spéléologie
A85: C02.09.04 | D85: Accident en montagne
A86: C02.09.05 | D86: Accident de parachutisme ou deltaplane
A87: C02.09.06 | D87: Accident d'activité nautique
A88: C02.09.07 | D88: Autre accident de sport ou de loisirs
A89: C02.10.00 | C89: Accident en milieu aquatique
A90: C02.10.01 | D90: Personne visible dans l'eau
A91: C02.10.02 | D91: Noyade
A92: C02.10.03 | D92: Personne sortie de l'eau suite à noyade
A93: C02.10.04 | D93: Engin nautique à la dérive avec présence humaine à bord
A94: C02.11.00 | C94: Chute
A95: C02.11.01 | D95: Chute de grande hauteur | E95: Chute de plus de 3 mètres (ou 1 étage)
A96: C02.11.02 | D96: Chute de faible hauteur | E96: Chute de moins de 3 mètres (y compris de sa hauteur)
A97: C02.12.00 | C97: Personne en difficulté
A98: C02.12.01 | D98: Personne ensevelie
A99: C02.12.02 | D99: Personne envasée, ensablée, ensilée
A100: C02.12.03 | D100: Personne bloquée en hauteur
...

Sheet Type de lieu
A1: Identifiant nomenclature | B1: HubSante.lieu
A2: Référentiel nomenclature | B2: CISU
A3: Nom Nomenclature | B3: Code_Type_de_lieu
A4: Nombre de niveau | B4: 3
A5: Description | B5: Décrit le type de lieu où se situe l'affaire/dossier
A6: Code | B6: Libellé niveau 1 | C6: Libellé niveau 2 | D6: Libellé niveau 3 | E6: Description | F6: Commentaire
A7: L01.00.00 | B7: Domicile
A8: L01.01.00 | C8: Maison particulière, pavillon
A9: L01.01.01 | D9: A l'intérieur d'une maison | E9: Enceinte fermée et couverte dont l’accès est potentiellement verrouillé, à renseigner en l’absence d’information plus précise sur la pièce où se situe la personne concernée
A10: L01.01.02 | D10: A l'extérieur d'une maison | E10: Abords, terrasse, jardin, … non couvert
A11: L01.01.03 | D11: Piscine / bassin d'une maison | E11: Privée, enterrée ou non, fixe ou non
A12: L01.01.04 | D12: Dépendance d'une maison | E12: Abri indépendant du domicile de type garage, atelier, abri de jardin, grange, etc.
A13: L01.01.05 | D13: Toiture/Combles d'une maison
A14: L01.02.00 | C14: Lieu d'habitation collectif ou foyer d'hébergement
A15: L01.02.01 | D15: A l'intérieur de l'immeuble (sans précision) | E15: Enceinte fermée et couverte dont l’accès est potentiellement verrouillé, à renseigner en l’absence d’information plus précise sur la pièce où se situe la personne concernée
A16: L01.02.02 | D16: A l'extérieur de l'immeuble | E16: Abords, terrasse, jardin, … non couvert
A17: L01.02.03 | D17: A l'intérieur d'un appartement
A18: L01.02.04 | D18: Entrée / couloir / espaces communs de l'immeuble | E18: Hors escalier
A19: L01.02.05 | D19: Ascenseur
A20: L01.02.06 | D20: Cave / sous-sol / garage /parking d'un immeuble d'habitation
A21: L01.02.07 | D21: Toiture de l'immeuble
A22: L01.02.08 | D22: Comble de l'immeuble
A23: L01.02.09 | D23: Piscine de l'immeuble | E23: Privée, enterrée ou non, fixe ou non
A24: L01.02.10 | D24: Escaliers de l'immeuble
A25: L01.02.11 | D25: Local technique de l'immeuble | E25: Chaufferie, gaine d'ascenseur
A26: L01.02.12 | D26: Dépendance de l'immeuble | E26: Abri indépendant du domicile de type garage, atelier, abri de jardin, grange, etc.
A27: L01.02.13 | D27: Local poubelle / vide ordure de l'immeuble
A28: L01.02.14 | D28: Balcon/terrasse de l'immeuble
A29: L01.03.00 | C29: Habitat spécifique
A30: L01.03.01 | D30: Péniche
A31: L01.03.02 | D31: Mobil-home
A32: L01.03.03 | D32: Habitat précaire
A33: L01.03.04 | D33: Campement
A34: L01.03.05 | D34: Grande demeure / château / manoir
A35: L01.03.06 | D35: Chaumière
A36: L01.04.00 | C36: Autre type de domicile
A37: L02.00.00 | B37: Circulation/transport
A38: L02.01.00 | C38: Voie publique hors voie rapide | E38: Voie sans aucune séparation de chaussée
A39: L02.01.01 | D39: Tunnel (hors voie rapide)
A40: L02.01.02 | D40: Piste cyclable
A41: L02.01.03 | D41: Pont/viaduc (hors voie rapide)
A42: L02.02.00 | C42: Voie rapide
A43: L02.02.01 | D43: Voie rapide (hors autoroute) | E43: Voie rapide présentant au moins 2 X 2 voies
A44: L02.02.02 | D44: Autoroute
A45: L02.02.03 | D45: Aire de repos ou de service sur voie rapide
A46: L02.02.05 | D46: Tunnel (voie rapide)
A47: L02.02.06 | D47: Pont/viaduc (voie rapide)
A48: L02.03.00 | C48: Voie ferrée/tramway/métro
A49: L02.03.01 | D49: Voie ferrée souterraine ou couverte
A50: L02.03.02 | D50: Voie ferrée aérienne
A51: L02.03.05 | D51: Passage à niveau
A52: L02.03.04 | D52: Pont/viaduc (voie ferrée)
A53: L02.04.00 | C53: Voie fluviale
A54: L02.04.01 | D54: Tunnel (voie fluviale)
A55: L02.04.02 | D55: Ecluse
A56: L02.05.00 | C56: A bord d’un moyen de transport | E56: Cette précision ne s'applique pas aux CNDF "accidents" qui se suffisent à elles-mêmes
A57: L02.05.01 | D57: A bord d'un véhicule léger ou fourgon | E57: Catégorie de véhicules qui regroupe les voitures de tourisme et les véhicules utilitaires (jusqu'à 3,5 tonnes)
A58: L02.05.02 | D58: A bord d'un poids lourd
A59: L02.05.03 | D59: A bord d'un bus / car / autocar | E59: Véhicule de grande dimension affecté au transport de passagers (Bus car autocar)
A60: L02.05.04 | D60: A bord d'un véhicule militaire | E60: véhicule militaire spécifique hors VL
A61: L02.05.05 | D61: A bord d'un convoi exceptionnel
A62: L02.05.06 | D62: A bord d'un métro
A63: L02.05.07 | D63: A bord d'un tramway
A64: L02.05.08 | D64: A bord d'un aéronef de marchandises | E64: Tout moyen de transport de marchandises par voie aérienne embarquant au moins 1 pilote à son bord
A65: L02.05.09 | D65: A bord d'un aéronef de voyageurs | E65: Tout moyen de transport de personnes par voie aérienne embarquant au moins 1 pilote à son bord
A66: L02.05.10 | D66: A bord d'un aeronef militaire | E66: Tout moyen de transport militaire par voie aérienne embarquant au moins 1 pilote à son bord
A67: L02.05.11 | D67: A bord d'un bateau de marchandises | E67: Tout moyen de transport de marchandises par voie ferroviaire
A68: L02.05.12 | D68: A bord d'un bateau de voyageurs | E68: Tout moyen de transport de personnes par voie ferroviaire
A69: L02.05.13 | D69: A bord d'un sous-marin
A70: L02.05.14 | D70: A bord d'un train de voyageurs | E70: Tout moyen de transport de personnes par voie ferroviaire
A71: L02.05.15 | D71: A bord d'un train de marchandises | E71: Tout moyen de transport de marchandises par voie ferroviaire
A72: L02.05.16 | D72: A bord d'un téléphérique ou télésiège
A73: L02.06.00 | C73: Aéroport / aérodrome
A74: L02.06.01 | D74: Aéroport - zone non accessible au public ou zone côté piste
A75: L02.06.02
A76: L02.06.03
A77: L02.06.04
A78: L02.06.05
A79: L02.06.06 | D79: Aérodrome – toutes zones
A80: L02.06.09 | D80: Aéroport - Zone de sûreté à accès réglementé | E80: Zone critique à accès réglementé
A81: L02.06.10 | D81: Base ou enceinte aérienne militaire | E81: Adaptation de la réponse opérationnelle et service à prévenir
A82: L02.07.00 | C82: Gare ferroviaire et routière | E82: Dont billetterie
A83: L02.07.01 | D83: Hall de gare
A84: L02.07.02 | D84: Quai de gare
A85: L02.07.04 | D85: Gare ou station souterraine
A86: L02.07.05 | D86: Gare ou station aérienne
A87: L02.07.06 | D87: Arrêt de bus / tramway
A88: L02.07.07 | D88: Voies de circulation de la gare
A89: L02.08.00 | C89: Autre type de lieu lié à la circulation ou au transport
A90: L02.08.01 | D90: Pont hors aquatique | E90: Ex: passerelle
A91: L02.08.02 | D91: Pont aquatique mer | E91: Ex: pont mobile
A92: L02.08.03 | D92: Pont aquatique eaux intérieures | E92: Ex: pont transbordeur, passerelle
A93: L02.09.00 | C93: Port/Quai/Embarcadère | E93: Adaptation de la réponse opérationnelle et service à prévenir
A94: L02.09.01 | D94: Port civil | E94: Adaptation de la réponse opérationnelle et service à prévenir
A95: L02.09.02 | D95: Port militaire | E95: Adaptation de la réponse opérationnelle et service à prévenir
A96: L03.00.00 | B96: Local d’activité professionnelle
A97: L03.01.00 | C97: Local administratif | E97: Ex : Bureau, back-office administratif d’un local commercial
A98: L03.02.00 | C98: Local agricole
A99: L03.02.01 | D99: Corps de ferme | E99: Concerne la partie habitable
A100: L03.02.02 | D100: Hangar agricole | E100: Concerne tout bâtiment hors habitation
...

Sheet Risque, menace et sensibilité
A1: Identifiant nomenclature | B1: HubSante.risque
A2: Référentiel nomenclature | B2: CISU
A3: Nom Nomenclature | B3: Code_Risque-Menace-Sensibilité
A4: Nombre de niveau | B4: 1
A5: Description | B5: Décrit les risques, menaces ou sensibilités de l'affaire/dossier
A6: Code | B6: Libellé niveau 1 | C6: Description | D6: Commentaire
A7: R01 | B7: Dommage exclusivement matériel | C7: Usage métier DGGN permettant la graduation matériel / corporel / mortel
A8: R02 | B8: Auteur(s) en fuite
A9: R03 | B9: Présence d’individu(s) ou public menaçant
A10: R04 | B10: Présence d’individu(s) muni(s) d’une arme blanche
A11: R05 | B11: Présence d’individu(s) muni(s) d’une arme à feu
A12: R06 | B12: Suspicion d'attaque terroriste
A13: R07 | B13: Présence de matière ou matériel dangereux | C13: Ex : armes, matière dangereuse non identifiée
A14: R08 | B14: Présence de matière radiologique ou nucléaire civile ou militaire | C14: A saisir si le caractère civil ou militaire n’est pas connu
A15: R11 | B15: Présence de matière bactériologique
A16: R12 | B16: Présence de matière chimique
A17: R13 | B17: Risque d'explosion, présence de gaz
A18: R14 | B18: Risque lié à l'incendie
A19: R15 | B19: Risque d'effondrement
A20: R16 | B20: Présence d'animal dangereux
A21: R17 | B21: Nuée d'insectes
A22: R18 | B22: Inondation
A23: R19 | B23: Risque électrique/ risque lié à une ligne HT ou THT | C23: HT / THT : Haute Tension / Très Haute Tension
A24: R20 | B24: Difficulté d’accès sur site | C24: Ex : milieu montagneux hors voie carrossable
A25: R21 | B25: Difficulté d’accès au patient/victime | C25: Ex : porte verrouillée
A26: R22 | B26: Gêne à la circulation
A27: R23 | B27: Implication d’un élus | C27: En vue d’un traitement avec remontée hiérarchique
A28: R24 | B28: Implication d’un agent public | C28: En vue d’un traitement sans remontée hiérarchique systématique
A29: R25 | B29: Implication d’une personnalité | C29: Ex : VIP
A30: R26 | B30: Implication de plusieurs personnes (2 à 10) | C30: En vue de permettre aux forces de sécurité d’adapter leur dispositif d’intervention. Les autres informations contextuelles (nature des personnes impliquées, attitude, …) sont à qualifier en champ libre. A aborder par l’opérateur en même temps que le nombre de patients/victimes.
A31: R27 | B31: Implication de nombreuses personnes (11 et+) | C31: En vue de permettre aux forces de sécurité d’adapter leur dispositif d’intervention. Les autres informations contextuelles (nature des personnes impliquées, attitude, …) sont à qualifier en champ libre. A aborder par l’opérateur en même temps que le nombre de patients/victimes.
A32: R28 | B32: Patient/Victime incarcéré
A33: R31 | B33: Patient/Victime dans l'eau
A34: R32 | B34: Patient/Victime confiné
A35: R33 | B35: Patient/Victime violent
A36: R34 | B36: Patient/Victime vulnérable | C36: Ex : personnes mineures
A37: R35 | B37: Patient/Victime contagieux | C37: Ex : prise en charge de patients tuberculeux
A38: R37 | B38: Situation instable/indéterminée | C38: En vue d’alerter les professionnels intervenant sur place d'un possible risque de dégradation de la situation (ex: reconnaissance sur site non achevée)
A39: R60 | B39: Risque d'explosion, présence de gaz (bouteilles)
A40: R61 | B40: Présence de matière ou matériel explosif
A41: R62 | B41: GPL ou carburation non conventionnelle
A42: R63 | B42: Engin Propulsion / Traction électrique
A43: R64 | B43: Levée de doute ou sinistre naissant | C43: Qualifie une situation pour laquelle les lieux les premiers moyens sur les lieux vont rencontrer des difficultés pour découvrir le sinistre. La découverte du sinitre ne sera pas flagrante
A44: R65 | B44: Présence de bétail
A45: R66 | B45: Présence d'animal domestique
A46: R67 | B46: Porte/accès verrouillé
A47: R68 | B47: Patient / victime ejecté
A48: R69 | B48: Patient/Victime non visible
A49: R70 | B49: Carence prestataire extérieur
A50: R71 | B50: Situation en profondeur | C50: En sous-sol/milieu difficile d'accès
A51: R72 | B51: Hauteur inférieure ou égale à 2 étages ( <= 8mètres) | C51: Conditionne le choix du vecteur à utiliser
A52: R73 | B52: Situation en milieu vicié | C52: Atmosphère irrrespirable
A53: R74 | B53: Locaux à sommeil
A54: R75 | B54: Gaz - Accident ou présence de travaux
A55: R76 | B55: Gaz - Ouvrage endommagé visible
A56: R77 | B56: Gaz - Ouvrage endommaé non visible
A57: R78 | B57: Gaz - Dégâts apparents sur la conduite de gaz
A58: R79 | B58: Gaz - Bruits, sifflements, souffle, vibrations ou projections
A59: R80 | B59: Gaz - Zone dense en population
A60: R81 | B60: Gaz - Grand rassemblement de public
A61: R82 | B61: Gaz - En sous-sol
A62: R83 | B62: Nombreux appels
A63: R84 | B63: Hauteur supérieure à 2 étages (> 8 mètres)
A64: R85 | B64: Hauteur supérieure à 7 étages (> 28 mètres)
... A67: R89 | B67: Victime face à une menace plus ou moins différée
A68: R90 | B68: Présence dans un lieu public non protégé | C68: Personne présente dans un lieu non protégé l'exposant au public ou à des conditions climatiques défavorable
A69: R91 | B69: Implication d’une autorité

Sheet Motif de recours médico-secouri
A1: Identifiant nomenclature | B1: HubSante.motif
A2: Référentiel nomenclature | B2: CISU
A3: Nom Nomenclature | B3: Code_Motif_patient-victime
A4: Nombre de niveau | B4: 3
A5: Description | B5: Décrit le motif de recours médico-secouriste.
A6: Code | B6: Libellé niveau 1 | C6: Libellé niveau 2 | D6: Libellé niveau 3 | E6: Description | F6: Commentaire
A7: M08.00.00 | B7: Personne inconsciente
A8: M08.01.00 | C8: Personne en arrêt ventilatoire
A9: M08.02.00 | C9: Personne en arrêt cardio-respiratoire
A10: M08.03.00 | C10: Personne inconsciente qui respire
A11: M09.00.00 | B11: Hémorragies / Saignements
A12: M09.01.00 | C12: Hémorragie ne pouvant être stoppée
A13: M09.01.01 | D13: Epitaxis non stoppée par compression
A14: M09.02.00 | C14: Hémorragie extériorisée
A15: M09.02.01 | D15: Hémorragie digestive (haute ou basse) extériorirée
A16: M09.02.02 | D16: Hémorragie extériorisée avec malaise
A17: M09.02.03 | D17: Crache du sang hémoptysie
A18: M09.02.04 | D18: Saignement stoppé par compression
A19: M09.02.05 | D19: Epistaxis stoppée par compression
A20: M09.03.00 | C20: Saignements bénins
A21: M09.03.01 | D21: Saignement bénin sans signe de gravité identifié
A22: M10.00.00 | B22: Problème circulatoire
A23: M10.01.00 | C23: Palpitations
A24: M10.02.00 | C24: Autres troubles circulatoires
A25: M10.02.01 | D25: Patient/victime choquée par défibrillateur implanté
A26: M10.02.02 | D26: Bradycardie < 50 ou tachycardie > 150
A27: M10.02.03 | D27: Pression Artérielle < 90 mmHg
A28: M10.02.04 | D28: Pression Artérielle > 160 mmHg
A29: M10.02.05 | D29: Autre trouble sans signe de gravité
A30: M11.00.00 | B30: Problème respiratoire
A31: M11.01.00 | C31: Détresse respiratoire
A32: M11.01.01 | D32: Détresse respiratoire avec asphyxie | E32: Moins de 4 syllabes ou mots courts, cyanose), ou obstruction complète
A33: M11.01.02 | D33: Epuisement respiratoire chez un nourrisson
A34: M11.02.00 | C34: Difficultés respiratoires
A35: M11.02.01 | D35: Respiration bruyante
A36: M11.02.02 | D36: Difficultés respiratoires avec sueurs ou altération de conscience
A37: M11.02.03 | D37: Difficultés respiratoires sans signe de gravité
A38: M11.03.00 | C38: Autres problèmes respiratoires
A39: M11.03.01 | D39: Problème isolé d'appareillage respiratoire ou canule
A40: M11.03.02 | D40: Corps étranger expulsé des poumons
A41: M11.03.03 | D41: Problème respiratoire avec obstruction partielle
A42: M11.03.04 | D42: Autres problème respiratoire sans signe de gravité
A43: M12.00.00 | B43: Problème neurologique
A44: M12.01.00 | C44: Suspicion AVC / AIT
A45: M12.01.01 | D45: Suspicion AVC / AIT avec trouble de conscience
A46: M12.01.02 | D46: Suspicion AVC / AIT sans céphalée ou vomissement ni trouble de la conscience
A47: M12.01.03 | D47: Suspicion AVC / AIT avec disparition des signes d'AVC à l'appel
A48: M12.02.00 | C48: Convulsions persistantes
A49: M12.03.00 | C49: Convulsion
A50: M12.03.01 | D50: Convulsions chez une femme enceinte
A51: M12.03.02 | D51: Convulsions avec fièvre chez l'enfant
A52: M12.03.03 | D52: En cours de réveil après convulsions
A53: M12.04.00 | C53: Trouble de la conscience
A54: M12.04.01 | D54: Trouble de la conscience chez un diabétique
A55: M12.04.02 | D55: Trouble de la conscience avec perte de connaissance initiale
A56: M12.04.03 | D56: Somnolent et capable de parler ou de répondre à des ordres simples
A57: M12.04.04 | D57: Confusion, désorientation
A58: M12.04.05 | D58: Autre trouble de la conscience sans signe de gravité
A59: M12.05.00 | C59: Malaise
A60: M12.05.01 | D60: Malaise sans signe de gravité
A61: M12.05.02 | D61: Malaise au cours d'un effort
A62: M12.05.03 | D62: Malaise avec perte de connaissance initiale
A63: M12.05.04 | D63: Malaise avec trouble de la conscience
A64: M12.06.00 | C64: Autre motif neurologique
A65: M12.06.01 | D65: Céphalées isolées
A66: M12.06.02 | D66: Céphalées avec vomissement
A67: M12.06.03 | D67: Autre motif neurologique sans signe de gravité
A68: M13.00.00 | B68: Traumatisme
A69: M13.01.00 | C69: Personne restant à terre suite à une chute
A70: M13.02.00 | C70: Polytraumatisme / traumatisme sévère
A71: M13.03.00 | C71: Traumatisme tête / cou
A72: M13.03.01 | D72: Traumatisme tête / cou avec perte de connaissance initiale ou troubles de la conscience
A73: M13.03.02 | D73: Traumatisme tête / cou sans signe de gravité
A74: M13.04.00 | C74: Traumatisme thorax
A75: M13.04.01 | D75: Traumatisme thorax avec gêne respiratoire
A76: M13.04.02 | D76: Traumatisme thorax sans signe de gravité
A77: M13.05.00 | C77: Traumatisme abdomen / bassin
A78: M13.05.01 | D78: Traumatisme abdomen / bassin violent
A79: M13.05.02 | D79: Traumatisme abdomen / bassin sans signe de gravité
A80: M13.06.00 | C80: Traumatisme membres
A81: M13.06.01 | D81: Traumatisme membre avec amputation
A82: M13.06.02 | D82: Fracture ouverte de membre
A83: M13.06.03 | D83: Fracture fermée de membre
A84: M13.06.04 | D84: Traumatisme avec déformation de membre
A85: M13.06.05 | D85: Traumatisme de membres sans signe de gravité
A86: M13.07.00 | C86: Traumatisme doigts - orteils
A87: M13.07.01 | D87: Traumatisme doigts / orteils avec amputation
A88: M13.07.02 | D88: Fracture ouverte de doigts / orteils
A89: M13.07.03 | D89: Fracture fermée doigts / orteils
A90: M13.07.04 | D90: Traumatisme doigts / orteils avec déformation
A91: M13.07.05 | D91: Traumatisme doigts / orteils sans signe de gravité
A92: M14.00.00 | B92: Plaies
A93: M14.01.00 | C93: Plaie pénétrante
A94: M14.01.01 | D94: Plaie pénétrante étendue
A95: M14.01.02 | D95: Plaies pénétrantes multiples
A96: M14.01.03 | D96: Plaie grave du crâne (scalp)
A97: M14.01.04 | D97: Plaie grave du visage
A98: M14.01.05 | D98: Plaie grave du cou
A99: M14.01.06 | D99: Plaie grave du thorax - abdomen
A100: M14.01.07 | D100: Plaie grave avec pâleur/soif/prostration
...

Sheet Etats du dossier
A1: Identifiant nomenclature | B1: HubSante.etat
A2: Référentiel nomenclature | B2: ENUM
A3: Nom Nomenclature | B3: Etats_Dossier
A4: Nombre de niveau | B4: 1
A5: Description | B5: Décrit la filière compétente pour traiter le dossier.
A6: Code | B6: Libellé niveau 1 | C6: Libellé niveau 2 | D6: Description | E6: Commentaire
A7: PROGRAM | B7: Programmé | D7: L'état « Programmé » est spécifique au DRM, il correspond à une création de dossier en avance de phase. Il est en particulier utilisé pour les TIH, dossiers pour lesquels la future régulation et prise en charge est connue. Un dossier à l’état « Programmé » contient la date et l’heure à laquelle le dossier doit s’activer.
A8: ACTIF | B8: Actif | D8: L'état « Actif » est un premier stade d’un dossier dans le cycle de vie (en dehors de l’état « Programmé » qui ne fait pas partie des états par lesquels passe l’ensemble des dossiers). L’état « Actif » qualifie le début de la prise en charge du dossier (au décroché de l’appel) et la phase de régulation médicale, cet état concerne l’ensemble des dossiers en cours d’instruction.
A9: ACHEVE | B9: Achévé | D9: L’état « Achevé » qualifie la fin de la phase active du dossier. Le dossier atteint l’état « Achevé » dès lors toutes les décisions possibles ont été prises et que les actions découlant de ces décisions ont été menées à leur terme : - Les patients sont arrivés à destination, - La prise en charge des patients a été assurée et est conforme à la décision prise, - Les véhicules sont arrivés à destination et ne transportent plus aucuns patients, - Les équipes d’intervention n’ont plus de patients en charge. Les dossiers à l’état « Achevé » restent modifiables par les agents du CRRA.
A10: VALIDE | B10: Validé | D10: L’état « Validé » marque la fin de la phase de régulation médicale. Le dossier passe automatiquement à l’état « Validé » dès lors : - Qu’il est complet (il contient toutes les informations et codifications obligatoires), - Qu’il est cohérent, - Que les identités des patients ont été vérifiées (contrôle optionnel). Tout dossier à l’état « Validé » reste modifiable (les notes et observations déjà présentes sont figées mais de nouvelles notes et observations peuvent être rédigées). Par ailleurs de nouvelles décisions peuvent être prises (en fonction de l’évolution de la situation du patient) ce qui a pour effet de renvoyer le dossier au début de son cycle de vie, à savoir à l’état « Actif ».
A11: CLOTURE | B11: Cloturé | D11: Etat « Clôturé » : tout dossier à l’état « Validé » passera à l’état « Clôturé » 24 heures après son passage à l’état « Actif ». Dès lors que le dossier est à l’état « Clôturé », le dossier n’est plus modifiable, sauf autorisation spécifique sur des champs précis. Par ailleurs, contrairement à l’état « Validé », un dossier à l’état « Clôturé » n’est plus réactivable (tout nouvel appel concernant le dossier qui nécessiterait une nouvelle prise de décision conduirait à l’ouverture d’un nouveau dossier). L’état « Clôturé » incarne la phase médico-administrative du dossier permettant la bonne tenue des tâches suivantes : - tâches médicales pour certains DRM : contrôles qualité, certificats médicaux, attestations, courriers au médecin traitant… - tâches de secrétariat et actions administratives : prescriptions de transport, contrôles qualité, courriers, pré facturations, facturations, etc.
A12: CLASSE | B12: Classé | D12: Etat « Classé » : le passage à l’état « Classé » incarne la fin de la phase médico-administrative. Le dossier atteint cet état dès lors qu’il est à l’état « Clôturé ». Tout dossier à l’état « Classé » n’est plus modifiable (seules des notes peuvent être ajoutées par certains utilisateurs autorisés). Le passage à l’état « Classé » est par ailleurs automatique 3 mois après l’ouverture du dossier.
A13: ARCHIVE | B13: Archivé | D13: Etat « Archivé » : un dossier passera à l’état « Archivé » dès lors qu’il est à l’état « Classé » et qu’il respecte toutes les obligations du test d’archivage. Dès lors que le dossier est « Archivé », toute modification de champs devient impossible. Le dossier n’est par ailleurs plus disponible dans le SI-Samu (les données utiles à des fins statistiques seront anonymisées dans le respect des règles en vigueur et conservées dans les bases de données existantes). L’archivage ne pourra être réalisé qu’après un délai minimal à respecter (ex : 2 ou 5 ans)

Sheet Nombre de patients-victimes
A1: Identifiant nomenclature | B1: HubSante.nbVictimes
A2: Référentiel nomenclature | B2: ENUM
A3: Nom Nomenclature | B3: NOMBRE_Patient_Victime
A4: Nombre de niveau | B4: 1
A5: Description | B5: Décrit le nombre de patient/victimes
A6: Code | B6: Libellé niveau 1 | C6: Libellé niveau 2 | D6: Description | E6: Commentaire
A7: 0 | B7: 0
A8: 1 | B8: 1
A9: PLUSIEURS | B9: PLUSIEURS
A10: BEAUCOUP | B10: BEAUCOUP
A11: INCONNU | B11: INCONNU
A12: NON DEFINI | B12: NON DEFINI

Sheet Type du patient-victime
A1: Identifiant nomenclature | B1: HubSante.patient
A2: Référentiel nomenclature | B2: ENUM
A3: Nom Nomenclature | B3: TYPE_Patient_Victime
A4: Nombre de niveau | B4: 1
A5: Description | B5: Décrit le type de patient/victime principal
A6: Code | B6: Libellé niveau 1 | C6: Libellé niveau 2 | D6: Description | E6: Commentaire
A7: NOURRISSON | B7: NOURRISSON
A8: ENFANT | B8: ENFANT
A9: ADULTE | B9: ADULTE
A10: SENIOR | B10: SENIOR
A11: ENCEINTE | B11: ENCEINTE

Sheet Attribution du dossier
A1: Identifiant nomenclature | B1: HubSante.attribution
A2: Référentiel nomenclature | B2: SI-SAMU
A3: Nom Nomenclature | B3: DEVENIRD
A4: Nombre de niveau | B4: 3
A5: Description | B5: Décrit le type de dossier, et son attribution
A6: Code | B6: Libellé niveau 1 | C6: Libellé niveau 2 | D6: Libellé niveau 3 | E6: Description | F6: Commentaire
A7: DRM | B7: DRM | E7: Dossier de régulation médicale
A8: DRM.MRU | C8: DRM MRU | E8: Dossier de type médecine d’urgence
A9: DRM.MRU.MU | D9: Régulation MU | E9: Dossier de type médecine d’urgence régulé par un médecin urgentiste. Le dossier devient de type DRM
A10: DRM.MRU.INDISPMU | D10: Régulation ML par indisponibilité MU | E10: Dossier de type médecine d'urgence régulé par un médecin libéral du fait de l’indisponibilité des MU. Le dossier devient de type DRM
A11: DRM.MRU.SSE | D11: Régulation de crise - NOVI | E11: Dossier relevant de la gestion de crise – NOmbreuses Victimes. Le dossier devient de type DRM
A12: DRM.MRU.PLANBLAN | D12: Régulation Plan Blanc | E12: Dossier régulé dans le cadre d’ un dispositif plan blanc. Le dossier devient de type DRM
A13: DRM.MRU.PCSAMU | D13: Régulation par un PC mobile | E13: Dossier régulé depuis un poste de commandement mobile. Le dossier devient de type DRM
A14: DRM.SPE | C14: DRM SPE
A15: DRM.SPE.DENT | D15: Régulation dentaire | E15: Dossier régulé par un chirurgien dentiste au sein du CRRA. Le dossier devient de type DRM
A16: DRM.SPE.GERIA | D16: Régulation gériatrique | E16: Dossier régulé par un gériatre au sein du CRRA. Le dossier devient de type DRM
A17: DRM.SPE.PEDIA | D17: Régulation pédiatrie | E17: Dossier régulé par un pédiatre au sein du CRRA. Le dossier devient de type DRM
A18: DRM.SPE.OBST | D18: Régulation obstétrique | E18: Dossier relevant d'une coordination périnatale. Le dossier devient de type DRM
A19: DRM.SPE.PSY | D19: Régulation psychiatrie | E19: Dossier régulé par un psychiatre au sein du CRRA. Le dossier devient de type DRM
A20: DRM.SPE.TOXICOL | D20: Régulation toxicologique | E20: Dossier régulé par un toxicologue au sein du CRRA. Le dossier devient de type DRM
A21: DRM.SPE.AUTRESPE | D21: Régulation autre spécialité
A22: DRM.MRL | C22: DRM MRL | E22: Dossier de type médecine libérale
A23: DRM.MRL.MG | D23: Régulation ML | E23: Dossier de type médecine libérale régulé par un médecin libéral. Le dossier devient de type DRM
A24: DRM.MRL.INDISPMG | D24: Régulation MU par indisponibilité ML | E24: Dossier de type médecine libérale régulé par un médecin urgentiste du fait de l’indisponibilité des ML. Le dossier devient de type DRM
A25: DRM.MRL.ABSML | D25: Régulation MU par absence de régulation ML | E25: Dossier de type médecine libérale régulé par un médecin urgentiste du fait de l’absence de régulation ML. Le dossier devient de type DRM
A26: DR | B26: DR | E26: Dossier de régulation
A27: DR.DREG | C27: Dossier Régulation | E27: Dossier de régulation
A28: DR.DREG.DRARM | D28: Pas d’acte de régulation médicale - Prise en charge ARM | E28: Dossier ne relevant pas de la régulation médicale et pas dans le cadre des autre cas identifié (voir cas suivant). Le dossier est de type DR
A29: DR.DREG.DRDAC | D29: Pas d’acte de régulation médicale - Prise en charge DAC
A30: DR.DREG.DRMED | D30: Pas d’acte de régulation médicale - Transmission d'informations sur un médecin (procédure dégradée) | E30: Dossier ne relevant pas de la régulation médicale – réponse apportée à une demande de renseignements sur un médecin. Le dossier est de type DR
A31: DR.DREG.DRPHARMA | D31: Pas d’acte de régulation médicale - Transmission d'informations sur une pharmacie | E31: Dossier ne relevant pas de la régulation médicale – réponse apportée à une demande de renseignements sur une pharmacie. Le dossier est de type DR
A32: DR.DREG.DRDENT | D32: Pas d’acte de régulation médicale - Transmission d'informations sur un dentiste | E32: Dossier ne relevant pas de la régulation médicale – réponse apportée à une demande de renseignements sur un dentiste. Le dossier est de type DR
A33: DR.DREG.DRINFO | D33: Pas d’acte de régulation médicale - Information générale | E33: Dossier ne relevant pas de la régulation médicale – réponse apportée à une demande de renseignements d’ordre général. Le dossier est de type DR
A34: DR.DREG.DOS-SIS | D34: Pas d’acte de régulation médicale - Appel pour les pompiers | E34: Dossier ne rentrant pas dans le cadre des missions du Samu et confié aux pompiers. Le dossier est de type DR
A35: DR.DREG.DOS-FDO | D35: Pas d’acte de régulation médicale - Appel pour les forces de l’ordre | E35: Dossier ne rentrant pas dans le cadre des missions du Samu et confié aux forces de l'ordre. Le dossier est de type DR
A36: D | B36: D | E36: Dossier
A37: D.D-MALV | C37: Erreur / Malveillant | E37: Dossier de type erreur ou appel malveillant
A38: D.D-MALV.ERR | D38: Erreur de numéro, erreur d'acheminement | E38: Le requérant s’est trompé de numéro de téléphone ou a mal été orienté par un interlocuteur précédent. Le dossier reste de type D
A39: D.D-MALV.NRP | D39: Appel raccroché / pas de réponse | E39: L’appel est raccroché ou sans réponse de l’appelant à l’ouverture du dossier. Le dossier reste de type D
A40: D.D-MALV.MALV | D40: Appel malveillant, canular | E40: Appel malveillant : insultes, canular, fausses informations. Il ne s’agit pas d’une erreur de numéro. Le dossier reste de type D
A41: D.D-MALV.FAX | D41: Tonalité de fax, porteuse | E41: Tonalité de fax ou d’une porteuse présente au décroché. Le dossier reste de type D
A42: D.D-MALV.ITERATIF | D42: Dossier existant, appel itératif (hors SI-Samu) | E42: Appels pour un dossier déjà existant. Entraine la recherche et l’ouverture du dossier préexistant avec rattachement de l’appel à ce dossier (option à supprimer dès l'intégration au SI-Samu)
A43: D.D-IDENT | C43: Appel identifié | E43: Dossier en rapport avec un appel qui n'est ni un DR ni un DRM
A44: D.D-IDENT.ADMIN | D44: Appel administratif | E44: Dossier ne relevant pas de la régulation médicale – et concerne la gestion administrative d’un dossier clôturé. Le dossier reste de type D
A45: D.D-IDENT.PERSO | D45: Appel personnel | E45: L’appel concerne une communication pour un membre du personnel et a un caractère privé. Le dossier reste de type D
A46: D.D-IDENT.AUTRE | D46: Autre type d’appel | E46: Autre type d’appel non régulé et relevant pas d’un problème médical, social ou sanitaire. Le dossier reste de type D

Sheet Priorité de régulation médicale
A1: Identifiant nomenclature | B1: HubSante.priorite
A2: Référentiel nomenclature | B2: SI-SAMU
A3: Nom Nomenclature | B3: PRIORITE
A4: Nombre de niveau | B4: 1
A5: Description | B5: Décrit la priorité de régulation médicale.
A6: Code | B6: Libellé niveau 1 | C6: Libellé niveau 2 | D6: Libellé niveau 3 | E6: Description | F6: Commentaire
A7: P0 | B7: Urgence vitale | E7: Régulation médicale pour une urgence vitale
A8: P1 | B8: Prioritaire | E8: Régulation médicale urgente et prioritaire
A9: P2 | B9: Non Urgent | E9: Régulation médicale non urgente (valeur attribuée par défaut)
A10: P3 | B10: Différé | E10: Régulation médicale différée
A11: NR | B11: Non régulé | E11: Pas d’acte de régulation médicale

Sheet Lieu - Source ou type d'id
A1: Identifiant nomenclature | B1: HubSante.idLieu
A2: Référentiel nomenclature | B2: ENUM
A3: Nom Nomenclature | B3: SOURCE_Id_Lieu
A4: Nombre de niveau | B4: 1
A5: Description | B5: Décrit le type d'idenfiant possible pour un lieu (société / établissement)
A6: Code | B6: Libellé niveau 1 | C6: Libellé niveau 2 | D6: Description | E6: Commentaire
A7: FINESS_ADMINISTRATIF | B7: FINESS_ADMINISTRATIF
A8: FINESS_GEOGRAPHIQUE | B8: FINESS_GEOGRAPHIQUE
A9: SIREN | B9: SIREN
A10: SIRET | B10: SIRET
A11: APE_NAF | B11: APE_NAF

Sheet Precision
A1: Identifiant nomenclature | B1: HubSante.precision
A2: Référentiel nomenclature | B2: ENUM
A3: Nom Nomenclature | B3: PRECISION
A4: Nombre de niveau | B4: 1
A5: Description | B5: Décrit le niveau de précision des coordonnées GPS envoyées
A6: Code | B6: Libellé niveau 1 | C6: Libellé niveau 2 | D6: Description | E6: Commentaire
A7: VILLE | B7: VILLE | D7: Précision à l'échelle de la ville
A8: RUE | B8: RUE | D8: Précision à l'échelle de la rue
A9: ADRESSE | B9: ADRESSE | D9: Adresse précise
A10: EXACTE | B10: EXACTE | D10: Point coordonnée GPS exact
A11: INCONNUE | B11: INCONNUE | D11: Précision de la localisation non évaluable par l'émetteur

Sheet Nom de la source
A1: Identifiant nomenclature | B1: HubSante.systeme
A2: Référentiel nomenclature | B2: ENUM
A3: Nom Nomenclature | B3: SOURCE_Loc
A4: Nombre de niveau | B4: 1
A5: Description | B5: Décrit le système fournissant le localisant
A6: Code | B6: Libellé niveau 1 | C6: Libellé niveau 2 | D6: Description | E6: Commentaire
A7: BAN | B7: BAN
A8: IGN | B8: IGN
A9: NEXSIS | B9: NEXSIS

Sheet Type d'objet
A1: Identifiant nomenclature | B1: HubSante.objetSource
A2: Référentiel nomenclature | B2: ENUM
A3: Nom Nomenclature | B3: TYPE_Objet_Sys
A4: Nombre de niveau | B4: 1
A5: Description | B5: Décrit le type d'objet dans le système
A6: Code | B6: Libellé niveau 1 | C6: Libellé niveau 2 | D6: Description | E6: Commentaire
A7: MANUEL | B7: MANUEL
A8: CARTE | B8: CARTE
A9: AUTRE | B9: AUTRE
A10: PHOTO | B10: PHOTO
A11: SITE_INTERNET | B11: SITE_INTERNET

Sheet Signalement
A1: Identifiant nomenclature | B1: HubSante.signalement
A2: Référentiel nomenclature | B2: ENUM
A3: Nom Nomenclature | B3: SIGNALEMENT
A4: Nombre de niveau | B4: 1
A5: Description | B5: Décrit le niveau de signalement de l'alerte
A6: Code | B6: Libellé niveau 1 | C6: Libellé niveau 2 | D6: Description | E6: Commentaire
A7: STANDARD | B7: STANDARD
A8: ATTENTION | B8: ATTENTION

Sheet Canal
A1: Identifiant nomenclature | B1: HubSante.canal
A2: Référentiel nomenclature | B2: ENUM
A3: Nom Nomenclature | B3: CONTACT_Canal
A4: Nombre de niveau | B4: 1
A5: Description | B5: Décrit le type de canal utilisé pour le contact
A6: Code | B6: Libellé niveau 1 | C6: Libellé niveau 2 | D6: Description | E6: Commentaire
A7: APPLICATION | B7: APPLICATION
A8: BAU | B8: BAU
A9: DAU | B9: DAU
A10: DEFIBRILLATEUR | B10: DEFIBRILLATEUR
A11: ECALL | B11: ECALL
A12: PERSONNE | B12: PERSONNE

Sheet Type de contact
A1: Identifiant nomenclature | B1: HubSante.typeCom
A2: Référentiel nomenclature | B2: ENUM
A3: Nom Nomenclature | B3: CONTACT_Type
A4: Nombre de niveau | B4: 1
A5: Description | B5: Décrit le type de contact
A6: Code | B6: Libellé niveau 1 | C6: Libellé niveau 2 | D6: Description | E6: Commentaire
A7: EMAIL | B7: EMAIL
A8: FAX | B8: FAX
A9: MSS | B9: MSS
A10: POSTAL | B10: POSTAL
A11: RADIO | B11: RADIO
A12: TEL | B12: TEL
A13: WEB | B13: WEB

Sheet Langue
A1: Identifiant nomenclature | B1: HubSante.langue
A2: Référentiel nomenclature | B2: ISO-639.1
A3: Nom Nomenclature | B3: LANGUE
A4: Nombre de niveau | B4: 1
A5: Description | B5: Décrit la langue parlée par l'appelant / le requérant. Source : https://www.loc.gov/standards/iso639-2/php/code_list.php
A6: Code | B6: Libellé niveau 1 | C6: Libellé niveau 2 | D6: Libellé niveau 3 | E6: Description | F6: Commentaire
A7: aa | B7: Afar | C7: afar
A8: ab | B8: Abkhazian | C8: abkhaze
A9: ae | B9: Avestan | C9: avestique
A10: af | B10: Afrikaans | C10: afrikaans
A11: ak | B11: Akan | C11: akan
A12: am | B12: Amharic | C12: amharique
A13: an | B13: Aragonese | C13: aragonais
A14: ar | B14: Arabic | C14: arabe
A15: as | B15: Assamese | C15: assamais
A16: av | B16: Avaric | C16: avar
A17: ay | B17: Aymara | C17: aymara
A18: az | B18: Azerbaijani | C18: azéri
... A189: zu | B189: Zulu | C189: zoulou

Sheet Type de requérant
A1: Identifiant nomenclature | B1: HubSante.typeAppelant
A2: Référentiel nomenclature | B2: SI-SAMU
A3: Nom Nomenclature | B3: TYPAPPLT
A4: Nombre de niveau | B4: 2
A5: Description | B5: Décrit le type de requérant/appelant
A6: Code | B6: Libellé niveau 1 | C6: Libellé niveau 2 | D6: Description | E6: Commentaire
A7: SUJET | B7: Le patient lui-même | D7: Le patient lui-même, victime de l’événement signalé et bénéficiaire des moyens qui pourraient être décidés même s’il a une des fonctions ou titres ci-dessous.
A8: FAMILLE | B8: Famille ou proche du patient | D8: Requérant qui se présente comme membre de la famille ou proche (concubin, compagnon, colocataire, ...) de la victime de l’événement signalé même s’il a un des titres ou une des fonctions ci-dessous.
A9: TIERS | B9: Autre particulier ou passant | D9: Particulier qui n’a pas une des fonctions ou titres ci-dessous et qui ne fait pas partie de la famille de la victime.
A10: POMPIER | B10: Pompier | D10: Le requérant est un pompier professionnel ou volontaire en activité et agissant dans le cadre de sa profession au moment de l’appel.
A11: AMBULANC | B11: Ambulancier | D11: Le requérant est un ambulancier agissant dans le cadre de sa profession au moment de l’appel.
A12: AMBULANC.AASC | C12: Secouriste aasc | D12: Pour tout secouriste actif d'une association aggrée de sécurité civile et n’est pas un professionnel de santé.
A13: AMBULANC.AUTRESEC | C13: Autre secouriste | D13: Secouriste du travail ou requerant qui se revendique secouriste
A14: SECOUR | B14: Secouriste actif | D14: Pour tout secouriste actif ( secouriste du travail ou agissant pour une association de secourisme) mais uniquement s’il est en activité et n’est pas un professionnel de santé.
A15: MED | B15: Médecin | D15: Regroupe les médecins de toute spécialité, de tout statut mais uniquement s’ils sont en activité et agissent dans le cadre de leur profession au moment de l’appel.
A16: MED.MEDSOS | C16: Médecin SOS ou association PDS | D16: Déclinaison du type Médecin : Regroupe les médecins SOS, uniquement s’ils sont en activité et agissent dans le cadre de leur profession au moment de l’appel.
A17: MED.MRL | C17: Médecin régulateur libéral | D17: Déclinaison du type Médecin : Regroupe les demandes issues des médecins régulateurs généralistes lorsque le DRM n’est pas encore créé dans le SI-Samu (par exemple quand il a été jusque-là uniquement renseigné dans un SI-PDSA).
A18: MED.EFFML | C18: Effecteur de médecine libérale | D18: Déclinaison du type Médecin : Regroupe les demandes issues des médecins effecteurs de médecine générale (hors médecins de SOS ou association de PDSA) lorsque le DRM n’est pas encore créé dans le SI-Samu (par exemple quand il a été jusque-là uniquement renseigné dans un SI-PDSA).
A19: SANTE | B19: Autre acteur de santé | D19: Regroupe tous les autres professionnels de santé, de toute spécialité, de tout statut mais uniquement s’ils sont en activité et agissent dans le cadre de leur profession au moment de l’appel.
A20: SANTE.INF | C20: Infirmier | D20: Regroupe les infirmiers de toute spécialité, de tout statut mais uniquement s’ils sont en activité et agissent dans le cadre de leur profession au moment de l’appel.
A21: SANTE.AIDESOIN | C21: Aide-soignant | D21: Regroupe les aides-soignants, de tout statut mais uniquement s’ils sont en activité et agissent dans le cadre de leur profession au moment de l’appel.
A22: SANTE.SF | C22: Sage-femme | D22: Regroupe les sage-femmes, de tout statut mais uniquement s’ils sont en activité et agissent dans le cadre de leur profession au moment de l’appel.
A23: SANTE.AIDEDOM | C23: Aide à domicile | D23: Regroupe les aides à domicile, de tout statut mais uniquement s’ils sont en activité et agissent dans le cadre de leur profession au moment de l’appel.
A24: SANTE.PHARMA | C24: Pharmacien | D24: Regroupe les pharmaciens, de tout statut mais uniquement s’ils sont en activité et agissent dans le cadre de leur profession au moment de l’appel.
A25: SANTE.DENTISTE | C25: Dentiste | D25: Regroupe les dentistes, de tout statut mais uniquement s’ils sont en activité et agissent dans le cadre de leur profession au moment de l’appel.
A26: SANTE.LABO | C26: Personnel de laboratoire | D26: Regroupe lespersonnels de laboratoires, de tout statut mais uniquement s’ils sont en activité et agissent dans le cadre de leur profession au moment de l’appel.
A27: FDO-MILI | B27: Policier Gendarme Militaire | D27: Regroupe tout policier, gendarme, militaire de tout statut et de tout grade mais uniquement s’il est en activité et n’est pas un professionnel de santé ou un secouriste actif.
A28: FDO-MILI.POL | C28: Policier
A29: FDO-MILI.GENDARM | C29: Gendarme
A30: FDO-MILI.MILI | C30: Militaire
A31: ADM-TUTL | B31: Membre d'une autorité administrative | D31: L’appelant est issu d’une autorité administrative (de tutelle) et appelle les services d’urgence dans le cadre de ses fonctions (ex : ARS, Ministère de la santé, HAS…)
A32: VIP | B32: VIP | D32: Personne publique, de notoriété ou élus Mais qui n'est pas une autorité administrative
A33: OBJCONNC | B33: Objets connectés | D33: L’appelant initial n’est pas une personne physique mais un objet connecté en mesure de passer des appels d’urgences (ex : automobile dans le cadre des appels e-call)
A34: AUTRE | B34: Autre type d’appelant | D34: Pour toutes les fonctions non prévues ci-dessus.
A35: INCONNU | B35: Type d'appelant indéterminé | D35: Si la fonction ou le titre de l'appelant est inconnu.

Sheet Difficultés de communication
A1: Identifiant nomenclature | B1: HubSante.communication
A2: Référentiel nomenclature | B2: SI-SAMU
A3: Nom Nomenclature | B3: PBAPL
A4: Nombre de niveau | B4: 1
A5: Description | B5: Décrit les difficultés de communication potentielles du requérant/appelant
A6: Code | B6: Libellé niveau 1 | C6: Libellé niveau 2 | D6: Libellé niveau 3 | E6: Description | F6: Commentaire
A7: AUCUNE | B7: Aucune difficulté de communication | E7: Aucune difficulté de communication rencontrée entre l’appelant et la personne qualifiant ou régulant le dossier.
A8: MUET | B8: Muet ou malentendant (troubles de la parole ou de l'audition) | E8: Difficultés de communication liées aux caractéristiques de l’appelant, muet ou ayant des troubles prononcés de l’élocution, malentendant ou ayant des troubles prononcés de l’audition ne lui permettant pas d’interagir dans de bonnes conditions avec son interlocuteur du CRRA
A9: VISION | B9: Malvoyant, troubles de la vision | E9: Difficultés de communication liées aux caractéristiques de l’appelant, malvoyant ou ayant des troubles prononcés de la vue ne lui permettant pas de décrire correctement la situation pour laquelle il appelle
A10: LANGUE | B10: Barrière de la langue (langue étrangère) | E10: Difficultés de communication avec l’appelant liées au fait que l’appelant ne comprend pas ou mal le français ou ne le parle pas ou mal
A11: PANIQUE | B11: Panique de l’appelant | E11: Difficultés de communication avec l’appelant liées à une situation de stress extrême ou de panique de l’appelant, du patient ou de l’entourage ne lui permettant pas de décrire correctement la situation pour laquelle il appelle
A12: HOSTILE | B12: Appelant hostile, agressif | E12: Difficultés de communication avec l’appelant liées à une situation d’hostilité ou d’agressivité de l’appelant ne permettant pas une bonne compréhension du problème pour lequel il appelle
A13: AGITE | B13: Incohérence, agitation, intoxication | E13: Patient psychiatrique ayant des difficultés pour exprimer sa plainte ou patient alcoolisé, agité et incohérent dans l’incapacité de formuler les raisons de son appel
A14: AUTRE | B14: Autres difficultés de communication | E14: Autres troubles humains ou techniques, de l’appelant ou de l’entourage, empêchant la bonne interaction entre l’appelant et la personne qualifiant ou régulant le dossier et la bonne compréhension de la situation pour laquelle il appelle
A15: IMPOSS | B15: Absence de communication | E15: Pas de communication possible avec l’appelant (ex : pas d'echange vocal, appel raccroché prématurement sans contre appel possible, ...)

Sheet Patient - type d'Id
A1: Identifiant nomenclature | B1: HubSante.typeIdPatient
A2: Référentiel nomenclature | B2: ENUM
A3: Nom Nomenclature | B3: TYPE_Id_Patient
A4: Nombre de niveau | B4: 1
A5: Description | B5: Décrit le type d'identifiant fourni
A6: Code | B6: Libellé niveau 1 | C6: Libellé niveau 2 | D6: Description | E6: Commentaire
A7: NIR | B7: NIR | D7: Numéro d'identification NIR ou NIA
A8: SINUS | B8: SINUS | D8: Numéro d'identification SINUS
A9: DOSSARD | B9: DOSSARD | D9: Numéro de dossard
A10: PLACE | B10: PLACE | D10: Numéro de place
A11: AUTRE | B11: AUTRE | D11: Autre identifiant

Sheet Sexe
A1: Identifiant nomenclature | B1: HubSante.sexe
A2: Référentiel nomenclature | B2: NOS
A3: Nom Nomenclature | B3: NOMENC_SEXE
A4: Nombre de niveau | B4: 1
A5: Description | B5: Décrit le sexe du patient
A6: Code | B6: Libellé niveau 1 | C6: Libellé niveau 2 | D6: Libellé niveau 3 | E6: Description | F6: Commentaire
A7: M | B7: Masculin | E7: Qualifie les individus de sexe masculin
A8: F | B8: Féminin | E8: Qualifie les individus de sexe féminin
A9: O | B9: Autre sexe (ni masculin, ni féminin) | E9: Qualifie les individus de troisième genre (individu considéré comme n ’étant ni homme ni femme, à la fois homme et femme, ou neutre)
A10: UN | B10: Inconnu | E10: Le sexe de la personne n'est pas connu

Sheet Niveau de soin
A1: Identifiant nomenclature | B1: HubSante.niveauSoin
A2: Référentiel nomenclature | B2: SI-SAMU
A3: Nom Nomenclature | B3: GRAVITE
A4: Nombre de niveau | B4: 1
A5: Description | B5: Décrit le niveau de soins : le plus grave est retenu pour qualifier le dossier/affaire. Pour chaque patient/victime, le motif spécifique est indiqué.
A6: Code | B6: Libellé niveau 1 | C6: Libellé niveau 2 | D6: Libellé niveau 3 | E6: Description | F6: Commentaire
A7: R1 | B7: Urgence Vitale | E7: Urgence vitale patente ou latente imposant l’envoi du Smur
A8: R2 | B8: Urgence vraie | E8: Urgence vraie sans détresse vitale nécessitant l’envoi d’un médecin, d’une ambulance ou d’un VSAV. Le délai d’intervention est immédiat par défaut ou contractualisé entre le médecin régulateur et le requérant
A9: R3 | B9: Continuité de soins | E9: Situation relevant de la continuité de soins. Le délai ne constituant pas un facteur de risque
A10: R4 | B10: Conseil ou PMT | E10: Situation pouvant être traitée par un conseil médical ou prescription médicamenteuse par téléphone

Sheet Role
A1: Identifiant nomenclature | B1: HubSante.role
A2: Référentiel nomenclature | B2: ENUM
A3: Nom Nomenclature | B3: ROLE
A4: Nombre de niveau | B4: 1
A5: Description | B5: Décrit le rôle de l'opérateur dans l'organisation à laquelle il appartient
A6: Code | B6: Libellé niveau 1 | C6: Libellé niveau 2 | D6: Description | E6: Commentaire
A7: AMBULANCIER | B7: Ambulancier | D7: L'opérateur est un ambulancier
A8: ARM | B8: ARM | D8: L'opérateur est un ARM
A9: INFIRMIER | B9: Infirmier | D9: L'opérateur est un infirmier
A10: MEDECIN | B10: Médecin | D10: L'opérateur est un médecin
A11: PILOTE | B11: Pilote | D11: L'opérateur est un pilote d'aéronef
A12: TCM | B12: Technicien de bord | D12: Assistant du pilote
A13: AUTRE | B13: Autre | D13: Le rôle de l'opérateur est connu, mais n'est pas détaillé dans la liste des valeurs fournie
A14: INCONNU | B14: Inconnu | D14: Le rôle de l'opérateur est inconnu

Sheet Type de decision
A1: Identifiant nomenclature | B1: HubSante.typeDecision
A2: Référentiel nomenclature | B2: SI-SAMU
A3: Nom Nomenclature | B3: TYPEDEC
A4: Nombre de niveau | B4: 2
A5: Description | B5: Décrit le type de décision prise
A6: Code | B6: Libellé niveau 1 | C6: Libellé niveau 2 | D6: Libellé niveau 3 | E6: Description | F6: Commentaire
A7: CONSEIL | B7: Conseil Médical | C7: #Conseil Médical | E7: Conduite à tenir donnée à distance par le médecin régulateur sans intervention d’un tiers. Le conseil médical peut être donné à la demande du patient ou à chaque fois que le médecin régulateur juge que l’appel ne nécessite pas un examen médical. Cette décision peut être accompagnée ou non d’une prescription médicamenteuse téléphonique.
A8: PMT | B8: Prescription médicamenteuse téléphonique | C8: #PMT | E8: Réalisation d'une prescription médicamenteuse téléphonique
A9: INTER | B9: Décision d’intervention | C9: #Intervention | E9: Décision qui implique l’envoi d’un moyen d’intervention (ressource mobile) : Smur, médical, paramédical, pompier ous transporteur sanitaire.
A10: ORIENT | B10: Décision d’orientation ou de transport | C10: #Orientation Transport | E10: La décision d’orientation est caractérisée par le fait de renseigner la destination du patient (vers un acteur de santé, vers une structure ou activité de soins, vers un autre lieu). La décision de transport permet, en complément, de décider de la prise en charge du transport du patient vers ce lieu de destination et de décider du niveau de soin du transport.
A11: PASPLUS | B11: Pas de décision supplémentaire | C11: #Décision | E11: En raison des décisions déjà prises par un tiers, des éventuels moyens d’intervention déjà présents sur place, le médecin régulateur en charge de la régulation du dossier ne prend pas de décision supplémentaire en attendant l’évolution de la situation.

Sheet Type de ressource
A1: Identifiant nomenclature | B1: HubSante.typeRessource
A2: Référentiel nomenclature | B2: SI-SAMU
A3: Nom Nomenclature | B3: TYPE_MOYEN | C3: on ne parle plus de moyens mais de ressources dans le DSF
A4: Nombre de niveau | B4: 2
A5: Description | B5: Décrit le type de moyen/ressources, dans un sens plus large que type de vecteur/véhicule. N.B. dans OPG pour les message EMSI.
A6: Code | B6: Libellé niveau 1 | C6: Libellé niveau 2 | D6: Libellé niveau 3 | E6: Description | F6: Commentaire
A7: SMUR | B7: Smur | E7: Ressources des SMUR
A8: SMUR.ADULT | C8: Smur Généraliste | F8: UMH
A9: SMUR.PED | C9: Smur Pédiatrique ou Néonat | F9: UMH-PED
A10: SMUR.UMH-S | C10: Smur Spécialisé | E10: Exemple UMH Obstétrique et autre UMH à venir | F10: UMH-S
A11: SMUR.CUMP | C11: Cellule d'Urgence Médico Psychologique | F11: CUMP
A12: HOSPIT | B12: Hospitaliers (hors Smur) | E12: Ressources relevant des établissements de santé, public ou privé, hors des ressources du SMUR
A13: LIBERAL | B13: Professionnels Libéraux | E13: Ressources relevant de la prise en charge par des professionnels libéraux
A14: LIBERAL.MG | C14: Médecin Généraliste
A15: LIBERAL.PHARM | C15: Pharmacien
A16: LIBERAL.INF | C16: Infirmier
A17: LIBERAL.KINE | C17: Kinésithérapeuthes
A18: LIBERAL.SOS | C18: Association de permanence de soins
A19: LIBERAL.MMG | C19: Maison médicale de garde
A20: LIBERAL.MSPD | C20: Maison de Santé Pluri Disciplinaire
A21: LIBERAL.MCS | C21: Médecin Correspondant de Samu
A22: LIBERAL.SPEMED | C22: Médecin autre spécialité
A23: LIBERAL.DENT | C23: Dentiste
A24: LIBERAL.LABO | C24: Laboratoire d'analyses médicales
A25: LIBERAL.AUTREPRO | C25: Autre professionnel de santé
A26: TSU | B26: Ambulanciers privés (Transporteurs Sanitaires Urgent) | E26: Ressources relevant des sociétés d'ambulances privées
A27: SIS | B27: Pompiers | E27: Ressources relevant des services d'incendie et de secours
A28: SIS.MEDSP | C28: Medecin Sapeur-Pompier
A29: SIS.ISP | C29: Infirmier Sapeur-Pompier
A30: SIS.SP | C30: Secouriste
A31: AASC | B31: Sécurité civile, secouriste | E31: Ensemble des ressources fixes ou mobiles relevant des organisations de secourisme
A32: FDO | B32: Force de l'Ordre et douanes | E32: Ensemble des ressources fixes ou mobiles relevant des forces de l’ordre (police nationale, municipale, gendarmerie nationaux et douanes)
A33: FDO.PN | C33: Police Nationale
A34: FDO.GEND | C34: Gendarmerie Nationale
A35: FDO.PM | C35: Police Municipale
A36: FDO.DOUANES | C36: Douane
A37: AUTRE | B37: Autres ressources | E37: Autres ressources ne relevant d’aucune autre catégorie définie
A38: AUTRE.ADM | C38: Institutions administratives et sociales
A39: AUTRE.DAE | C39: Défibrillateur Automatique
A40: AUTRE.AUTRE | C40: Autre moyen

Sheet Type de vecteurs
A1: Identifiant nomenclature | B1: HubSante.typeVecteur
A2: Référentiel nomenclature | B2: SI-SAMU
A3: Nom Nomenclature | B3: TYPE_VECTEUR
A4: Nombre de niveau | B4: 2
A5: Description | B5: Décrit le type de vecteur/véhicule ou de ressource mobilisée, avec plus de précision que simplement le type de ressources. Utilisée exclusivement en inter-santé (cf. EMSI-OPG pour 15-NexSIS)
A6: Code | B6: Libellé niveau 1 | C6: Libellé niveau 2 | D6: Libellé niveau 3 | E6: Description | F6: Commentaire
A7: AASC | B7: AASC
A8: AASC.VLSC | C8: Vehicule Leger de Sécurité Civile | E8: Hybride
A9: AASC.VPSP | C9: Véhicule de Premiers Secours à Personnes | E9: Transporte
A10: AASC.AUTRESC | C10: Autre vecteur de Sécurité Civile | E10: Hybride
A11: AUTREVEC | B11: AUTRE
A12: AUTREVEC.APIED | C12: A pied | E12: Transporte
A13: AUTREVEC.AVION | C13: Avion | E13: Transporte
A14: AUTREVEC.PERSO | C14: Moyen personnel sans précsion | E14: Transporte
A15: AUTREVEC.TAXI | C15: Taxi et assimilés | E15: Transporte
A16: AUTREVEC.TRAIN | C16: Train | E16: Transporte
A17: AUTREVEC.TRANSP | C17: Transports en commun | E17: Transporte
A18: AUTREVEC.AUTRE | C18: Autre vecteur sans transport | E18: Ne transporte pas
A19: AUTREVEC.AUTRETRA | C19: Autre vecteur de transport | E19: Transporte
A20: FSI | B20: FSI
A21: FSI.HELIFSI | C21: Hélicoptère Forces de l’Ordre | E21: Hybride
A22: FSI.VLFSI | C22: VL des FSI | E22: Hybride
A23: FSI.FFSI | C23: Fourgon des FSI | E23: Hybride
A24: FSI.VHFSI | C24: Autre vecteur des FSI | E24: Hybride
A25: LIB | B25: LIB
A26: LIB.MEDV | C26: Médecin | E26: Ne transporte pas
A27: LIB.INF | C27: Infirmier | E27: Ne transporte pas
A28: LIB.AUTREPRO | C28: Autre professionnel de santé | E28: Ne transporte pas
A29: SIS | B29: SIS
A30: SIS.DRAGON | C30: Hélicoptère sécurité civile | E30: Transporte
A31: SIS.AVSC | C31: Avion sécurité civile | E31: Transporte
A32: SIS.FEUSIS | C32: Moyens incendie du SIS | E32: Ne transporte pas
A33: SIS.GRIMP | C33: Vehicule du GRIMP et montagne | E33: Ne transporte pas
A34: SIS.NAVISIS | C34: Moyen nautique du SIS | E34: Hybride
A35: SIS.PCSIS | C35: Poste de commandement | E35: Ne transporte pas
A36: SIS.SRSIS | C36: Moyens de secours routiers du SIS | E36: Ne transporte pas
A37: SIS.VCH | C37: Véhicule intervention chimique | E37: Ne transporte pas
A38: SIS.VLCG | C38: Véhicule léger chef de groupe | E38: Ne transporte pas
A39: SIS.VLISP | C39: Véhicule léger infirmier SP | E39: Ne transporte pas
A40: SIS.VLMSP | C40: Véhicule léger Médecin SP | E40: Ne transporte pas
A41: SIS.VLSIS | C41: Véhicule léger autre usage | E41: Ne transporte pas
... A47: SIS.AUTRESIS | C47: Autre moyen du SIS | E47: Hybride
A48: SMUR | B48: SMUR
A49: SMUR.VLM | C49: Véhicule Léger Médicalisé | E49: Ne transporte pas
A50: SMUR.VL | C50: Véhicule de liaison Smur | E50: Ne transporte pas
A51: SMUR.PSM1 | C51: Véhicule logistique transport PSM1 | E51: Ne transporte pas
A52: SMUR.PSM2 | C52: Véhicule logistique transport PSM2 | E52: Ne transporte pas
A53: SMUR.PSM3 | C53: Véhicule logistique transport PSM3 | E53: Ne transporte pas
A54: SMUR.PSMP | C54: Véhicule logistique transport PSM pédiatrique | E54: Ne transporte pas
A55: SMUR.VPC | C55: Véhicule Poste de Commandement et ou d’évacuation SAMU | E55: Ne transporte pas
A56: SMUR.AR | C56: Ambulance de réanimation | E56: Transporte
A57: SMUR.AR-BAR | C57: Ambulance de réanimation Bariatrique | E57: Transporte
A58: SMUR.AR-PED | C58: Ambulance de réanimation Pédiatrique | E58: Transporte
A59: SMUR.HELISMUR | C59: HéliSmur | E59: Transporte
A60: SMUR.HELISAN | C60: Hélicoptère de transport sanitaire | E60: Transporte
... A63: SMUR.NAVISMUR | C63: NaviSmur | E63: Transporte
A64: TSU | B64: TSU
A65: TSU.VSL | C65: Véhicule Sanitaire Léger | E65: Transporte
A66: TSU.AMB-GV | C66: Ambulance privée grand contenant - type A | E66: Transporte
A67: TSU.AMB-PV | C67: Ambulance privée petit contenant - type C | E67: Transporte
A68: TSU.AMB-BAR | C68: Ambulance privée - type bariatrique | E68: Transporte
A69: TSU.AMB | C69: Ambulance de catégorie non définie | E69: Transporte

Sheet Niveau de prise en charge
A1: Identifiant nomenclature | B1: HubSante.typePEC
A2: Référentiel nomenclature | B2: SI-SAMU
A3: Nom Nomenclature | B3: NIVSOIN
A4: Nombre de niveau | B4: 1
A5: Description | B5: Décrit le niveau de prise en charge exigé.
A6: Code | B6: Libellé niveau 1 | C6: Libellé niveau 2 | D6: Libellé niveau 3 | E6: Description | F6: Commentaire
A7: MED | B7: Médicalisé | E7: L'équipage du vecteur est composé d'au moins un médecin
A8: PARAMED | B8: Paramédicalisé | E8: L'équipage du vecteur ne comporte pas de médecin. Il est uniquement composé d'infirmier(e)s.
A9: SECOURS | B9: Secouriste | E9: L'équipage du vecteur ne comporte que des secouristes professionnnels ni médecin, ni infimier
A10: SANS | B10: Sans soins | E10: Le moyen de transport ne comporte aucun acteur de santé (transport par moyen personnel, taxi, transport en commun, ...)

Sheet Type de destination
A1: Identifiant nomenclature | B1: HubSante.typeOrientation
A2: Référentiel nomenclature | B2: ENUM
A3: Nom Nomenclature | B3: TYPE_Destination
A4: Nombre de niveau | B4: 1
A5: Description | B5: Décrit la filière compétente pour traiter le dossier.
A6: Code | B6: Libellé niveau 1 | C6: Libellé niveau 2 | D6: Description | E6: Commentaire
A7: URGENCES | B7: Service d’urgences d’un établissement de sante
A8: REA-USI | B8: Service de réanimation ou de soins intensifs
A9: SANTE | B9: Autres services d’un établissement de sante
A10: CABINET | B10: Cabinet d’un professionnel de sante
A11: DOMICILE | B11: Domicile
A12: EPHAD | B12: EPHAD ou Long séjour
A13: AUTRE | B13: Autre

Sheet Effet à obtenir
A1: Identifiant nomenclature | B1: HubSante.effet
A2: Référentiel nomenclature | B2: CISU
A3: Nom Nomenclature | B3: Code_Effet_a_obtenir
A4: Nombre de niveau | B4: 2
A5: Description | B5: Décrit les effets à obtenir utilisés uniquement entre SAMU, en intersanté.
A6: Code | B6: Libellé niveau 1 | C6: Libellé niveau 2 | D6: Description | E6: Commentaire
A7: SAP | B7: Demander une prise en charge secouriste | D7: Demander l'intervention d'une équipe secouriste / ambulance privée
A8: REGUL | B8: Demander une régulation médicale | D8: Demander la régulation médicale du dossier par un médecin régulateur (cas de partage d'activité - exemples : régulation spécialisée, régulation déportée la nuit, délestage, atypie locale )
A9: CUMP | B9: Demander un soutien médico psychologique | D9: Demander l'intervention de la CUMP
A10: SMUR | B10: Demander une prise en charge de médecine d'urgence | D10: Demander l'intervention d'une équipe SMUR
A11: MG | B11: Demander une prise en charge de médecine générale | D11: Demander l'obtention d'une consultation ou une visite du MG (uniquement pour lien 15-15)
A12: PARAMED | B12: Demander une prise en charge para médicale | D12: Demander l'intervention d'une équipe paramédicale (UMHP).
A13: SAMU | B13: Autre demande de concours au SAMU | D13: Détails à préciser dans le texte libre de la demande de ressources
A14: RELEVE | B14: Demander de relever une personne | D14: Demander de relever une personne
A15: NOVI | B15: Demander une prise en charge de nombreux patients/victimes | D15: Demander une prise en charge de nombreux patients/victimes
A16: TIH | B16: Demander un transfert interétablissement | D16: Demander un transfert interétablissement
A17: BRANCARD | B17: Demander une aide au brancardage | D17: Demander une aide au brancardage
A18: BARIA | B18: Demander un transport bariatrique | D18: Demander un transport bariatrique

Sheet Cadre conventionnel
A1: Identifiant nomenclature | B1: HubSante.cadre
A2: Référentiel nomenclature | B2: CISU
A3: Nom Nomenclature | B3: CADRE_CONV
A4: Nombre de niveau | B4: 1
A5: Description | B5: Décrit le cadre conventionnel dans lequel s'inscrit une demande de ressources. Codes inter-santé uniquement (voir EMSI pour lien 15-Nexsis).
A6: Code | B6: Libellé niveau 1 | C6: Libellé niveau 2 | D6: Libellé niveau 3 | E6: Description | F6: Commentaire
A7: DRSIS | B7: Départ réflexe SIS | E7: Engagement d'un moyen du SIS dans le cadre strict des départs réflexes prévu à l'annexe 1 du réferentiel SAP-AMU (Situations cliniques, circonstances particulières, Voie Publique)
A8: MISSION | B8: Propres missions | E8: Engagement d'un moyen du partenaire résultant de ses missions propres (hors départ reflexe du SIS)
A9: ITSP | B9: Carence pour ITSP | E9: Engagement d'un VSAV par carence résultant d'une Indisponibilité de Transporteur sanitaire Privé
A10: CARENCE | B10: Carence pour autre motif | E10: Engagement d'un VSAV par carence résultant d'un autre motif
A11: CONVENT | B11: Convention locale | E11: Engagement d'un moyen du partenaire, hors mission propre et hors carence, mais prévu dans une convention départementale ou régionale (notamment convention bi-tripartite)
A12: SPE | B12: Convention spécifique | E12: Engagement d'un moyen du partenaire résultant d'une convention spécifique (transport bariatrique, ….)
A13: HORS | B13: Hors de ses missions | E13: Engagement d'un moyen du partenaire hors cadre conventionnel, hors de ses missions et hors d'un cadre conventionnel
A14: AUTRE1 | B14: Autre cas 1 | E14: Engagement d'un partenaire dans un nouveau cadre ou en test
A15: AUTRE2 | B15: Autre cas 2 | E15: Engagement d'un partenaire dans un nouveau cadre ou en test
A16: AUTRE3 | B16: Autre cas 3 | E16: Engagement d'un partenaire dans un nouveau cadre ou en test

Sheet Delai d'intervention
A1: Identifiant nomenclature | B1: HubSante.delai
A2: Référentiel nomenclature | B2: SI-SAMU
A3: Nom Nomenclature | B3: DELAI
A4: Nombre de niveau | B4: 1
A5: Description | B5: Décrit le délai d'intervention attendu ou souhaité pour une ressource ou un vecteur.
A6: Code | B6: Libellé niveau 1 | C6: Libellé niveau 2 | D6: Description | E6: Commentaire
A7: DEL0 | B7: Immédiatement | D7: La ressource doit être disponible et engagée immédiatement | E7: 1
A8: ASAP | B8: Dès que disponible | D8: La ressource doit être engagée dès qu'elle est disponible, elle doit être dans tous les cas arrivée sur les lieux dans un délai maximum de 1 heure | E8: 2
A9: 30M | B9: Délai maxi 30 minutes | D9: Le déclenchement se fait au bon vouloir de la force qui gère la ressource mais avec une présence de la ressource sur place dans un délai maximum de 30 minutes | E9: 3
A10: 45M | B10: Délai maxi 45 minutes | D10: Le déclenchement se fait au bon vouloir de la force qui gère la ressource mais avec une présence de la ressource sur place dans un délai maximum de 45 minutes | E10: 4
A11: 1H | B11: Délai maxi 1 heure | D11: Le déclenchement se fait au bon vouloir de la force qui gère la ressource mais avec une présence de la ressource sur place dans un délai maximum de 1 heures | E11: 5
A12: 2H | B12: Délai maxi 2 heures | D12: Le déclenchement se fait au bon vouloir de la force qui gère la ressource mais avec une présence de la ressource sur place dans un délai maximum de 2 heures | E12: 6
A13: 4H | B13: Délai maxi 4 heures | D13: Le déclenchement se fait au bon vouloir de la force qui gère la ressource mais avec une présence de la ressource sur place dans un délai maximum de 4 heures | E13: 7
A14: 8H | B14: Délai maxi 8 heures | D14: Le déclenchement se fait au bon vouloir de la force qui gère la ressource mais avec une présence de la ressource sur place dans un délai maximum de 8 heures | E14: 8
A15: 12H | B15: Délai maxi 12 heures | D15: Le déclenchement se fait au bon vouloir de la force qui gère la ressource mais avec une présence de la ressource sur place dans un délai maximum de 12 heures | E15: 9
A16: 24H | B16: Délai maxi 24 heures | D16: Le déclenchement se fait au bon vouloir de la force qui gère la ressource mais avec une présence de la ressource sur place dans un délai maximum de 24 heures | E16: 10
A17: RDV | B17: HH:MM | D17: Une présence sur les lieux à un horaire précis (l'horaire est à indiquer dans le freetext) | E17: 11

Sheet Annulation DR
A1: Identifiant nomenclature | B1: HubSante.etatDemande
A2: Référentiel nomenclature | B2: ENUM
A3: Nom Nomenclature | B3: STATUS_DR
A4: Nombre de niveau | B4: 1
A5: Description | B5: Décrit l'état de l'annulation de demande de ressources
A6: Code | B6: Libellé niveau 1 | C6: Libellé niveau 2 | D6: Description | E6: Commentaire
A7: ANNULEE | B7: Annulation de la demande de ressources | D7: La demande de concours est annulée dans son intégralité

Sheet Reponse demande ressources
A1: Identifiant nomenclature | B1: HubSante.reponseDemande
A2: Référentiel nomenclature | B2: ENUM
A3: Nom Nomenclature | B3: REPONSE
A4: Nombre de niveau | B4: 1
A5: Description | B5: Décrit la réponse à une demande de ressources
A6: Code | B6: Libellé niveau 1 | C6: Libellé niveau 2 | D6: Libellé niveau 3 | E6: Description | F6: Commentaire
A7: ACCEPTEE | B7: ACCEPTEE | E7: La demande est acceptée, sans réserve ni modifications. Si un délai maximum était indiqué dans la demande, alors celui si est considéré comme accepté.
A8: PARTIELLE | B8: PARTIELLE | E8: La demande est acceptée, avec réserves ou modifications. Par exemple, si le délai de réponse est différent de celui souhaité dans la demande. Toute modification ou réserve doit être précisée dans la réponse (en freetext si l'information ne peut pas être communiquée de manière structurée)
A9: REFUSEE | B9: REFUSEE | E9: La demande est refusée, le motif de refus est à préciser dans le freetext
A10: DIFFEREE | B10: DIFFEREE | E10: La demande a été reçue mais n'est pas encore traitée. La réponse sera envoyée ultérieurement.

Sheet Statut du vecteur
A1: Identifiant nomenclature | B1: HubSante.statutVecteur
A2: Référentiel nomenclature | B2: SI-SAMU
A3: Nom Nomenclature | B3: STATUS_VECTEUR
A4: Nombre de niveau | B4: 1
A5: Description | B5: Décrit le statut du vecteur/véhicule mobilisé
A6: Code | B6: Libellé niveau 1 | C6: Libellé niveau 2 | D6: Libellé niveau 3 | E6: Description | F6: Commentaire
A7: DECISION | B7: Décision | E7: Prise de décision de recours à la ressource sollicitée (gerer au niveau du PSAP) | F7: 00-DECISION
A8: DECLENCHE | B8: Déclenché | E8: Déclenchement de l’intervention selon le dispositif habituel prévu
A9: DEPART | B9: Début d’intervention | E9: Départ de la base ou de réengagement de la ressource pour se rendre sur le lieu d'intervention | F9: 01-PARTI
A10: ANNULE | B10: Annulation de l’intervention | E10: Annulation d'une mission déjà engagée avant arrivée sur les lieux
A11: ARRIVEE | B11: Arrivée sur les lieux | E11: Arrivée à l’adresse du lieu d’intervention | F11: 02-SLL
A12: PEC | B12: Début de prise en charge | E12: Arrivée auprès du patient/victime d'au moins un membre de l'équipe d'intervention et début de prise en charge
A13: BILAN | B13: Transmission du bilan | E13: Le bilan est transmis en vue de l’orientation du patient/victime | F13: 03-MESSAGE
A14: ORIENTAT | B14: Transmission de la destination | E14: L’orientation du patient/victime est transmise à l’équipe d'intervention
A15: TRANSP | B15: Départ des lieux | E15: Départ de l’adresse du lieu d’intervention du moyen assurant le transport du patient/victime | F15: 05-TRANSPORT
A16: ETAPE1 | B16: Etape de transit 1 | E16: Arrivée à la première étape du moyen de transport avec le patient en charge dans le cas d’un transit notamment vers un lieu d’examen ou d’imagerie
A17: TRANSP2 | B17: Départ étape 1 | E17: Départ de la première étape du moyen de transport, en charge du patient/victime
A18: ETAPE2 | B18: Etape de transit 2 | E18: Arrivée à la deuxième étape du moyen de transport avec le patient/victime en charge dans le cas d’un transit notamment vers un lieu d’examen ou d’imagerie
A19: TRANSP3 | B19: Départ étape 2 | E19: Départ de la deuxième étape du moyen de transport, en charge du patient/victime
A20: DESTIN | B20: Arrivée à destination | E20: Arrivée du moyen de transport à l’entrée du service ou se fera le relais de prise en charge du patient/victime | F20: 06-DESTIN
A21: FINPEC | B21: Fin de prise en charge | E21: La responsabilité de la prise en charge du patient/victime s’achève | F21: 24-FIN MED
A22: RETOUR | B22: Quitte la destination | E22: L’équipe d'intervention quitte le lieu de destination du patient/victime ou le lieu d’intervention (en l’absence de transport du patient/victime). La ressource est disponible pour être réengagée | F22: 25-QTTE HOP
A23: RET-BASE | B23: Retour à la base | E23: L'équipe et en route vers sa base
A24: REN-BASE | B24: Rentrée à la base | E24: L’équipe est de retour à sa base

Sheet Etape message
A1: Identifiant nomenclature | B1: HubSante.etape
A2: Référentiel nomenclature | B2: ENUM
A3: Nom Nomenclature | B3: Etape_Message
A4: Nombre de niveau | B4: 1
A5: Description | B5: Décrit les différentes étapes d'intégration et de consultation du dossier dans un système
A6: Code | B6: Libellé niveau 1 | C6: Libellé niveau 2 | D6: Description | E6: Commentaire
A7: RECU | B7: Dossier reçu | D7: Le dossier a bien été reçu et est en cours d'intégration
A8: ERREUR | B8: Dossier en erreur | D8: La création ou intégration du dossier est en erreur
A9: INTEGRE | B9: Dossier intégré | D9: Le dossier est bien créé et intégré dans le système de destination finale
A10: CONSULTE | B10: Dossier consulté | D10: Le dossier a été ouvert par un utilisateur humain (à la première ouverture uniquement)
A11: SUPPRIME | B11: Dossier supprimé | D11: Le dossier dossier a été effacé/supprimé dans le système émetteur

Sheet #Type de devenir du patient
A1: Identifiant nomenclature
A2: Référentiel nomenclature | B2: SI-SAMU
A3: Nom Nomenclature | B3: NOMENC_DEVENIR_PAT
A4: Nombre de niveau | B4: 1
A5: Description | B5: Décrit le devenir du patient
A6: Code | B6: Libellé niveau 1 | C6: Libellé niveau 2 | D6: Libellé niveau 3 | E6: Description | F6: Commentaire
A7: OK | B7: Accord du service d'orientation | E7: Devenir issu de la décision d'orientation + modalité d'exécution
A8: TEMP | B8: Accord sous condition (en attente d'avis ou d'examen complémentaire ou d'affectation vers le service adapté) | E8: Devenir issu de la décision d'orientation + modalité d'exécution
A9: SEUL | B9: Laissé seul | E9: Devenir issu de la décision d'orientation + Type de laissé sur place
A10: AFAMILLE | B10: Laissé à la famille ou entourage | E10: Devenir issu de la décision d'orientation + Type de laissé sur place
A11: AMED | B11: Confié à un médecin | E11: Devenir issu de la décision d'orientation + Type de laissé sur place
A12: AFDO | B12: Confié aux Forces de l'ordre | E12: Devenir issu de la décision d'orientation + Type de laissé sur place
A13: ATIERS | B13: Confié à autre personne | E13: Devenir issu de la décision d'orientation + Type de laissé sur place
A14: MOYPERSO | B14: Retour à domicile - Transporté par ses propres moyens | E14: Devenir issu de la décision d'orientation + mode de transport
A15: VECTEUR | B15: Retour à domicile - Transporté par le vecteur d'intervention ou de transport envoyé par le CRRA | E15: Devenir issu de la décision d'orientation + mode de transport
A16: REFPAT | B16: Retour à domicile - Refus du patient, patient laissé sur place | E16: Devenir issu de la décision d'orientation + motif de refus
A17: REFFAM | B17: Retour à domicile - Refus de l'entourage, patient laissé sur place | E17: Devenir issu de la décision d'orientation + motif de refus
A18: PASREAKO | B18: DCD sans réanimation - non examiné par médecin | E18: Devenir issu de l'information relative au décès du patient
... A25: RAS | B25: Pas de prise en charge nécessaire | E25: Devenir issu de la décision d'orientation + Type de laissé sur place
